{
"metadata": {
    "version": {
        "essentia": "2.1-beta6-dev",
        "essentia_git_sha": "v2.1_beta5-234-g8aeca169",
        "extractor": "music 2.0"
    },
    "audio_properties": {
        "analysis": {
            "equal_loudness": 0,
            "length": 30.0599994659,
            "sample_rate": 44100,
            "start_time": 0,
            "downmix": "mix"
        },
        "bit_rate": 360000,
        "length": 30.0599994659,
        "lossless": 1,
        "number_channels": 1,
        "replay_gain": -9.2617931366,
        "sample_rate": 22500,
        "codec": "pcm_s16le",
        "md5_encoded": "494eee901c5d2fa05374ab2e3488145f"
    },
    "tags": {
        "file_name": "MT0008455201.wav"
    }
},
"lowlevel": {
    "average_loudness": 0.892912685871,
    "barkbands_crest": {
        "dmean": 2.2347548008,
        "dmean2": 3.72435164452,
        "dvar": 4.08385848999,
        "dvar2": 10.19647789,
        "kurt": -0.466099500656,
        "max": 22.0862312317,
        "mean": 13.4291582108,
        "median": 13.3066473007,
        "min": 3.91230773926,
        "skew": 0.0679535344243,
        "var": 11.2861442566
    },
    "barkbands_flatness_db": {
        "dmean": 0.0380476377904,
        "dmean2": 0.050805080682,
        "dvar": 0.00113881588914,
        "dvar2": 0.00191496883053,
        "kurt": 0.674426078796,
        "max": 0.783846795559,
        "mean": 0.332653969526,
        "median": 0.302395969629,
        "min": 0.0795626267791,
        "skew": 1.05899691582,
        "var": 0.0192244071513
    },
    "barkbands_kurtosis": {
        "dmean": 11.8309640884,
        "dmean2": 18.3924732208,
        "dvar": 594.980773926,
        "dvar2": 1340.31164551,
        "kurt": 86.2742080688,
        "max": 508.374298096,
        "mean": 25.6830215454,
        "median": 19.9024162292,
        "min": -1.58682703972,
        "skew": 7.60228013992,
        "var": 1053.29174805
    },
    "barkbands_skewness": {
        "dmean": 0.879436850548,
        "dmean2": 1.35574007034,
        "dvar": 1.05878829956,
        "dvar2": 2.40874695778,
        "kurt": 11.0453004837,
        "max": 17.5539493561,
        "mean": 3.68899202347,
        "median": 3.63803100586,
        "min": -1.94932866096,
        "skew": 1.70628845692,
        "var": 2.4736969471
    },
    "barkbands_spread": {
        "dmean": 4.9489774704,
        "dmean2": 7.56155729294,
        "dvar": 74.9905853271,
        "dvar2": 172.921234131,
        "kurt": 6.30280399323,
        "max": 64.82421875,
        "mean": 8.04447460175,
        "median": 4.10163021088,
        "min": 0.205591738224,
        "skew": 2.43365836143,
        "var": 103.423789978
    },
    "dissonance": {
        "dmean": 0.0229211971164,
        "dmean2": 0.0342375189066,
        "dvar": 0.000536617182661,
        "dvar2": 0.00124776281882,
        "kurt": 2.55105400085,
        "max": 0.499758064747,
        "mean": 0.428682684898,
        "median": 0.449328094721,
        "min": 0.158483117819,
        "skew": -1.61717665195,
        "var": 0.00369680230506
    },
    "dynamic_complexity": 4.49724531174,
    "erbbands_crest": {
        "dmean": 2.08072137833,
        "dmean2": 3.25091767311,
        "dvar": 3.71944642067,
        "dvar2": 8.48250102997,
        "kurt": 0.725340127945,
        "max": 27.0304679871,
        "mean": 10.172706604,
        "median": 9.01267623901,
        "min": 2.62677550316,
        "skew": 1.01354146004,
        "var": 21.7824783325
    },
    "erbbands_flatness_db": {
        "dmean": 0.023399759084,
        "dmean2": 0.0268709696829,
        "dvar": 0.000502298702486,
        "dvar2": 0.000711176602636,
        "kurt": 0.657746553421,
        "max": 0.552119255066,
        "mean": 0.256504684687,
        "median": 0.23484992981,
        "min": 0.101444020867,
        "skew": 1.07057321072,
        "var": 0.00864668469876
    },
    "erbbands_kurtosis": {
        "dmean": 4.97582817078,
        "dmean2": 7.67184638977,
        "dvar": 267.901580811,
        "dvar2": 648.010192871,
        "kurt": 28.1128921509,
        "max": 269.30279541,
        "mean": 8.78970146179,
        "median": 0.503374218941,
        "min": -1.97693657875,
        "skew": 4.99435186386,
        "var": 858.301208496
    },
    "erbbands_skewness": {
        "dmean": 0.64916151762,
        "dmean2": 0.939197778702,
        "dvar": 0.592935442924,
        "dvar2": 1.29236793518,
        "kurt": 7.19900417328,
        "max": 12.7732772827,
        "mean": 1.63079226017,
        "median": 1.23227250576,
        "min": -1.70675134659,
        "skew": 2.34302711487,
        "var": 3.795181036
    },
    "erbbands_spread": {
        "dmean": 11.4951334,
        "dmean2": 16.267288208,
        "dvar": 217.137329102,
        "dvar2": 403.613311768,
        "kurt": 0.244628429413,
        "max": 147.166534424,
        "mean": 41.4868469238,
        "median": 39.0185317993,
        "min": 0.526540458202,
        "skew": 0.565769970417,
        "var": 655.760375977
    },
    "hfc": {
        "dmean": 4.98429822922,
        "dmean2": 7.43555450439,
        "dvar": 143.588973999,
        "dvar2": 342.788726807,
        "kurt": 21.3552207947,
        "max": 157.025344849,
        "mean": 9.96988296509,
        "median": 6.18897724152,
        "min": 1.09323008787e-16,
        "skew": 3.87128186226,
        "var": 194.913574219
    },
    "loudness_ebu128": {
        "integrated": -17.7144985199,
        "loudness_range": 6.84009647369,
        "momentary": {
            "dmean": 0.60956788063,
            "dmean2": 0.684903919697,
            "dvar": 0.471657276154,
            "dvar2": 0.391018658876,
            "kurt": 3.04392671585,
            "max": -14.3795013428,
            "mean": -20.1423721313,
            "median": -17.6939640045,
            "min": -44.3230819702,
            "skew": -1.81794369221,
            "var": 31.9513034821
        },
        "short_term": {
            "dmean": 0.147446960211,
            "dmean2": 0.0840373337269,
            "dvar": 0.0230090096593,
            "dvar2": 0.00697019603103,
            "kurt": 0.455631256104,
            "max": -15.6199522018,
            "mean": -18.4072628021,
            "median": -17.5972442627,
            "min": -25.6923961639,
            "skew": -1.16302895546,
            "var": 6.1818189621
        }
    },
    "melbands_crest": {
        "dmean": 2.02609324455,
        "dmean2": 3.28660750389,
        "dvar": 3.8615899086,
        "dvar2": 9.94814968109,
        "kurt": -0.0109655857086,
        "max": 27.1534519196,
        "mean": 16.2002124786,
        "median": 16.2918281555,
        "min": 1.8189663887,
        "skew": 0.13357552886,
        "var": 13.5087347031
    },
    "melbands_flatness_db": {
        "dmean": 0.0440432652831,
        "dmean2": 0.0516237318516,
        "dvar": 0.00165706302505,
        "dvar2": 0.00257091736421,
        "kurt": 0.264377117157,
        "max": 0.8961378932,
        "mean": 0.403476983309,
        "median": 0.368332266808,
        "min": 0.00729033583775,
        "skew": 0.866376817226,
        "var": 0.0291315540671
    },
    "melbands_kurtosis": {
        "dmean": 22.8479576111,
        "dmean2": 36.3332672119,
        "dvar": 2192.70898438,
        "dvar2": 5302.80908203,
        "kurt": 80.4779129028,
        "max": 942.956298828,
        "mean": 53.5794754028,
        "median": 41.8514137268,
        "min": -1.34434449673,
        "skew": 7.22933578491,
        "var": 3414.5324707
    },
    "melbands_skewness": {
        "dmean": 1.07281863689,
        "dmean2": 1.68145668507,
        "dvar": 1.60259485245,
        "dvar2": 3.72612929344,
        "kurt": 8.00986671448,
        "max": 20.6876049042,
        "mean": 5.00058507919,
        "median": 4.84499931335,
        "min": -0.118124485016,
        "skew": 1.46766459942,
        "var": 4.29794025421
    },
    "melbands_spread": {
        "dmean": 3.4757566452,
        "dmean2": 5.31537866592,
        "dvar": 55.9783706665,
        "dvar2": 104.923408508,
        "kurt": 74.0216140747,
        "max": 137.936218262,
        "mean": 6.0457482338,
        "median": 3.4271903038,
        "min": 0.274808883667,
        "skew": 6.44634771347,
        "var": 78.2200164795
    },
    "pitch_salience": {
        "dmean": 0.0720251500607,
        "dmean2": 0.111983589828,
        "dvar": 0.00461950153112,
        "dvar2": 0.0103605603799,
        "kurt": -0.345239877701,
        "max": 0.81305783987,
        "mean": 0.472729146481,
        "median": 0.48918864131,
        "min": 0.0733937397599,
        "skew": -0.328528344631,
        "var": 0.0182903315872
    },
    "silence_rate_20dB": {
        "dmean": 0,
        "dmean2": 0,
        "dvar": 0,
        "dvar2": 0,
        "kurt": -3,
        "max": 1,
        "mean": 1,
        "median": 1,
        "min": 1,
        "skew": 0,
        "var": 0
    },
    "silence_rate_30dB": {
        "dmean": 0.00154440151528,
        "dmean2": 0.00309119001031,
        "dvar": 0.00154201628175,
        "dvar2": 0.00462722685188,
        "kurt": 1291.00061035,
        "max": 1,
        "mean": 0.999228417873,
        "median": 1,
        "min": 0,
        "skew": -35.958316803,
        "var": 0.000771009654272
    },
    "silence_rate_60dB": {
        "dmean": 0.0108108110726,
        "dmean2": 0.0216383300722,
        "dvar": 0.0106941442937,
        "dvar2": 0.0211696457118,
        "kurt": 2.95422029495,
        "max": 1,
        "mean": 0.128086417913,
        "median": 0,
        "min": 0,
        "skew": 2.22585630417,
        "var": 0.111679203808
    },
    "spectral_centroid": {
        "dmean": 242.528305054,
        "dmean2": 357.234649658,
        "dvar": 214854.671875,
        "dvar2": 391863.78125,
        "kurt": 96.6049728394,
        "max": 11185.7119141,
        "mean": 560.043640137,
        "median": 369.121673584,
        "min": 127.344161987,
        "skew": 6.37646007538,
        "var": 320651
    },
    "spectral_complexity": {
        "dmean": 3.20617771149,
        "dmean2": 4.7032456398,
        "dvar": 32.4232406616,
        "dvar2": 65.9931945801,
        "kurt": 4.39029216766,
        "max": 55,
        "mean": 10.0756168365,
        "median": 7,
        "min": 0,
        "skew": 1.96100580692,
        "var": 85.1670913696
    },
    "spectral_decrease": {
        "dmean": 2.13453676956e-09,
        "dmean2": 3.34988481399e-09,
        "dvar": 8.61382628367e-18,
        "dvar2": 2.17647828949e-17,
        "kurt": 1.03245735168,
        "max": 3.1908166345e-29,
        "mean": -7.25145721248e-09,
        "median": -6.76870648419e-09,
        "min": -3.59236373981e-08,
        "skew": -0.857218921185,
        "var": 3.04631263577e-17
    },
    "spectral_energy": {
        "dmean": 0.00832183752209,
        "dmean2": 0.01305034291,
        "dvar": 0.000137015493237,
        "dvar2": 0.000342010840541,
        "kurt": 1.29339933395,
        "max": 0.14167766273,
        "mean": 0.0282729845494,
        "median": 0.0263383742422,
        "min": 9.79549462428e-21,
        "skew": 0.920181274414,
        "var": 0.000472545390949
    },
    "spectral_energyband_high": {
        "dmean": 0.000460980430944,
        "dmean2": 0.000733574852347,
        "dvar": 1.86671513802e-06,
        "dvar2": 4.73693580716e-06,
        "kurt": 44.3783454895,
        "max": 0.0164565872401,
        "mean": 0.000397351192078,
        "median": 2.36935120483e-05,
        "min": 7.21914609464e-21,
        "skew": 5.81862878799,
        "var": 1.58663465299e-06
    },
    "spectral_energyband_low": {
        "dmean": 0.00512830773368,
        "dmean2": 0.00834109541029,
        "dvar": 4.09870517615e-05,
        "dvar2": 0.000109033317131,
        "kurt": 0.313003778458,
        "max": 0.0636648088694,
        "mean": 0.0144381299615,
        "median": 0.0123957972974,
        "min": 3.89324029753e-23,
        "skew": 0.853547751904,
        "var": 0.000130240499857
    },
    "spectral_energyband_middle_high": {
        "dmean": 0.000623126630671,
        "dmean2": 0.000887833768502,
        "dvar": 2.04521575142e-06,
        "dvar2": 4.27023724114e-06,
        "kurt": 18.4616088867,
        "max": 0.0206174049526,
        "mean": 0.00113719329238,
        "median": 0.000429315463407,
        "min": 1.32916110456e-21,
        "skew": 3.64429092407,
        "var": 3.74845899387e-06
    },
    "spectral_energyband_middle_low": {
        "dmean": 0.00566456792876,
        "dmean2": 0.0089383199811,
        "dvar": 7.88252436905e-05,
        "dvar2": 0.000207389850402,
        "kurt": 2.55329656601,
        "max": 0.105408228934,
        "mean": 0.0166270080954,
        "median": 0.0129135129973,
        "min": 2.1899952554e-22,
        "skew": 1.34738528728,
        "var": 0.00022803414322
    },
    "spectral_entropy": {
        "dmean": 0.328716576099,
        "dmean2": 0.385857611895,
        "dvar": 0.105512015522,
        "dvar2": 0.157586783171,
        "kurt": 0.152076721191,
        "max": 9.81597042084,
        "mean": 6.22480821609,
        "median": 6.46038532257,
        "min": 3.0482673645,
        "skew": -0.806196212769,
        "var": 1.40943539143
    },
    "spectral_flux": {
        "dmean": 0.0212319940329,
        "dmean2": 0.0326499193907,
        "dvar": 0.000706881168298,
        "dvar2": 0.00125919643324,
        "kurt": 2.76763868332,
        "max": 0.296139836311,
        "mean": 0.0574989542365,
        "median": 0.0474783405662,
        "min": 9.89721915534e-11,
        "skew": 1.46154356003,
        "var": 0.00205917353742
    },
    "spectral_kurtosis": {
        "dmean": 11.6225919724,
        "dmean2": 17.7909793854,
        "dvar": 694.053100586,
        "dvar2": 1586.25622559,
        "kurt": 26.4519081116,
        "max": 615.299377441,
        "mean": 26.977678299,
        "median": 5.86750650406,
        "min": -1.18416559696,
        "skew": 4.77151536942,
        "var": 4537.88964844
    },
    "spectral_rms": {
        "dmean": 0.00069520866964,
        "dmean2": 0.0010737509001,
        "dvar": 6.18127614871e-07,
        "dvar2": 1.46340983065e-06,
        "kurt": -0.542133569717,
        "max": 0.0117567898706,
        "mean": 0.00475133443251,
        "median": 0.0050691193901,
        "min": 3.09137199346e-12,
        "skew": -0.18329846859,
        "var": 5.00829219163e-06
    },
    "spectral_rolloff": {
        "dmean": 269.455108643,
        "dmean2": 469.387176514,
        "dvar": 948022.375,
        "dvar2": 1771684.625,
        "kurt": 215.698883057,
        "max": 18798.4863281,
        "mean": 438.175292969,
        "median": 258.3984375,
        "min": 129.19921875,
        "skew": 12.377612114,
        "var": 892594.5625
    },
    "spectral_skewness": {
        "dmean": 0.732728719711,
        "dmean2": 1.04431462288,
        "dvar": 0.859777569771,
        "dvar2": 1.97979044914,
        "kurt": 9.64812469482,
        "max": 21.2498531342,
        "mean": 2.81928467751,
        "median": 1.79392647743,
        "min": -0.181693121791,
        "skew": 2.90845036507,
        "var": 9.2228307724
    },
    "spectral_spread": {
        "dmean": 683540.875,
        "dmean2": 843524.0625,
        "dvar": 3.06985199206e+12,
        "dvar2": 3.16777352397e+12,
        "kurt": 202.196624756,
        "max": 51758640,
        "mean": 3014767.75,
        "median": 2795056.5,
        "min": 145991.609375,
        "skew": 10.6548185349,
        "var": 5.30761121792e+12
    },
    "spectral_strongpeak": {
        "dmean": 0.205389499664,
        "dmean2": 0.351344078779,
        "dvar": 0.0462142676115,
        "dvar2": 0.116407983005,
        "kurt": 1.85853528976,
        "max": 2.15017437935,
        "mean": 0.563772201538,
        "median": 0.524004817009,
        "min": 2.0611707896e-09,
        "skew": 1.02521920204,
        "var": 0.120594121516
    },
    "zerocrossingrate": {
        "dmean": 0.00879320967942,
        "dmean2": 0.0104659730569,
        "dvar": 0.000375835137675,
        "dvar2": 0.000423021439929,
        "kurt": 155.851699829,
        "max": 0.525390625,
        "mean": 0.0250097196549,
        "median": 0.01806640625,
        "min": 0.00537109375,
        "skew": 9.38498020172,
        "var": 0.000743242620956
    },
    "barkbands": {
        "dmean": [0.000131875698571, 0.000642180908471, 0.00368550163694, 0.0025621985551, 0.00376945454627, 0.000388765067328, 0.000425928243203, 0.000121547607705, 6.64007529849e-05, 4.80512426293e-05, 4.78829497297e-05, 4.8185534979e-05, 4.24673089583e-05, 2.65628223133e-05, 5.74581536057e-05, 8.02130452939e-05, 0.000163835764397, 0.000114753267553, 0.000115916525829, 0.000181757379323, 0.000123950827401, 9.10072922125e-05, 6.59374127281e-05, 6.43881139695e-05, 2.50807061093e-05, 6.63675947532e-10, 6.95214774638e-10],
        "dmean2": [0.000194103384274, 0.00104884873144, 0.0059434347786, 0.00433380063623, 0.00583692966029, 0.000615361903328, 0.000664998719003, 0.000198376917979, 9.87936655292e-05, 7.67999663367e-05, 7.80276168371e-05, 7.56752997404e-05, 6.85886552674e-05, 4.41235461039e-05, 8.8564818725e-05, 0.000127258696011, 0.00025182304671, 0.000171619991306, 0.000171786232386, 0.00029207742773, 0.000202314724447, 0.000145262049045, 0.000106182211312, 0.000107117804873, 4.21303629992e-05, 1.20388155e-09, 1.25949262131e-09],
        "dvar": [9.42857099062e-08, 2.37342305809e-06, 2.25517505896e-05, 1.90758346434e-05, 3.74593801098e-05, 6.38234837425e-07, 1.01217722204e-06, 5.37322684124e-08, 2.37972805905e-08, 1.19549730115e-08, 1.18177574393e-08, 1.28826620482e-08, 1.36632118952e-08, 5.25089483006e-09, 1.59385180609e-08, 3.51338158566e-08, 1.27112429027e-07, 9.55292094318e-08, 9.11139039772e-08, 3.2159306329e-07, 1.93345400135e-07, 7.9697002775e-08, 3.95832167044e-08, 5.21971585954e-08, 7.17104109427e-09, 1.82163410217e-18, 1.88567111647e-18],
        "dvar2": [2.0844278481e-07, 5.99612121732e-06, 5.85813941143e-05, 5.40434266441e-05, 8.99296355783e-05, 1.4558214616e-06, 2.52039058068e-06, 1.40053558084e-07, 4.76503210223e-08, 3.18538404542e-08, 3.11787680118e-08, 3.02298843735e-08, 3.71384309972e-08, 1.35496689424e-08, 3.99627424486e-08, 8.75627890196e-08, 2.61299959448e-07, 2.12951064782e-07, 2.05306648127e-07, 8.3119118699e-07, 5.05132220496e-07, 1.99556694724e-07, 1.01252616957e-07, 1.38082413059e-07, 1.86292243853e-08, 5.58322801158e-18, 5.7301981541e-18],
        "kurt": [29.7703094482, 52.1625556946, 0.532476186752, 6.51514911652, 5.5090637207, 18.8266639709, 22.1896457672, 7.71231174469, 20.1883792877, 44.0615921021, 18.1196727753, 19.1443271637, 43.5355796814, 52.3942756653, 41.5470123291, 28.3426322937, 26.8872375488, 26.6732025146, 34.6572799683, 55.038848877, 138.839355469, 45.0493392944, 42.3077697754, 145.963470459, 51.2705383301, 42.7711448669, 34.2256126404],
        "max": [0.00360352825373, 0.0206799097359, 0.0437003448606, 0.0437239035964, 0.0644828304648, 0.0173481460661, 0.0183123499155, 0.00236049620435, 0.00229256041348, 0.0017739427276, 0.00138065801002, 0.00148732645903, 0.0016311329091, 0.00111487985123, 0.00234999554232, 0.00297328992747, 0.00530456285924, 0.00373219093308, 0.0039063426666, 0.00635229516774, 0.00785381905735, 0.00300940033048, 0.00241647078656, 0.00407841103151, 0.000877927814145, 1.59791628818e-08, 1.50346792793e-08],
        "mean": [0.000136044385727, 0.00066800886998, 0.00932889897376, 0.0058819623664, 0.00838077906519, 0.00102094293106, 0.000944616796914, 0.000238548411289, 0.000118438430945, 7.79960610089e-05, 7.94203515397e-05, 8.7742912001e-05, 6.48603090667e-05, 3.7810565118e-05, 8.49931166158e-05, 0.000125015503727, 0.000246821175097, 0.000149026687723, 0.000131333334139, 0.000160651325132, 0.00010883079085, 7.61469564168e-05, 5.36097613804e-05, 5.07491822646e-05, 1.9726334358e-05, 5.33771304934e-10, 5.5896554052e-10],
        "median": [1.11982171802e-05, 0.000182118907105, 0.00770625751466, 0.00357767869718, 0.00574545701966, 0.000445426063379, 0.000253578822594, 8.95567500265e-05, 1.61054776981e-05, 3.4282609704e-05, 2.31775775319e-05, 2.26188640227e-05, 1.9464212528e-05, 7.21712831364e-06, 2.2353582608e-05, 3.30217662849e-05, 6.63933024043e-05, 1.75379354914e-05, 1.68215483427e-05, 1.3655231669e-05, 4.66706023872e-06, 2.06413847081e-06, 2.1114797164e-06, 9.8520672509e-07, 2.24670770876e-07, 1.02468727947e-10, 1.04944483659e-10],
        "min": [1.21987951548e-23, 3.31171381076e-24, 2.0812627703e-23, 2.02020355573e-24, 4.65476527912e-23, 1.90268864273e-23, 5.3202798932e-23, 4.10572250671e-23, 3.27126228572e-23, 7.71169784343e-23, 4.81613821577e-24, 4.61917408389e-23, 4.61888662297e-23, 5.0530059299e-23, 1.16040770204e-22, 1.52198481163e-22, 1.3544666012e-22, 1.27748412671e-22, 2.80693320333e-22, 2.90428747427e-22, 4.76765922638e-22, 3.90021414348e-22, 6.31685229239e-22, 8.83050240972e-22, 9.83161309414e-22, 1.76323544011e-21, 2.13981930945e-21],
        "skew": [4.71475172043, 5.91684579849, 0.973588943481, 2.44276928902, 2.00992131233, 3.42231178284, 3.83287167549, 2.4403090477, 3.97408223152, 4.90027618408, 3.52366781235, 3.74856281281, 5.29879713058, 5.71972417831, 4.72554016113, 4.56452417374, 4.32958698273, 4.56921291351, 5.06811857224, 6.54298830032, 9.38524436951, 6.03275489807, 5.73431158066, 9.42021846771, 6.44489908218, 5.36209630966, 4.90876960754],
        "var": [1.18920148395e-07, 2.20492665903e-06, 6.1938437284e-05, 5.30517718289e-05, 8.28036136227e-05, 2.42977444032e-06, 2.79408982351e-06, 1.1825617463e-07, 6.78016149891e-08, 1.60183581954e-08, 1.87968982601e-08, 2.64166857278e-08, 1.55384913825e-08, 6.50895826126e-09, 2.50358933584e-08, 6.71638460403e-08, 2.38675625042e-07, 1.3406564392e-07, 1.11396651903e-07, 2.63551669377e-07, 1.5458481073e-07, 6.74497684372e-08, 3.26759703739e-08, 3.89241101573e-08, 5.53149392957e-09, 1.43576727111e-18, 1.5183001473e-18]
    },
    "erbbands": {
        "dmean": [0.0196540635079, 0.175780132413, 2.70335292816, 7.82386302948, 11.1384963989, 13.4583597183, 9.65266990662, 3.1526529789, 6.18810987473, 5.19713068008, 1.8244382143, 1.60028886795, 1.5486344099, 1.59666907787, 1.58981692791, 2.15873813629, 1.97367811203, 1.30868697166, 1.46696579456, 3.99370956421, 6.82386732101, 6.75817394257, 5.52427959442, 6.51053762436, 6.28574228287, 8.46592330933, 5.49738454819, 5.29649972916, 3.45547485352, 2.38928723335, 1.79437530041, 1.30181515217, 1.11920547485, 0.542468369007, 0.0239167716354, 0.000774209853262, 6.75456176396e-05, 1.1391533917e-05, 5.95165192863e-06, 9.73732676357e-06],
        "dmean2": [0.0303896758705, 0.296165645123, 4.4095044136, 12.985789299, 19.3893413544, 20.3042640686, 14.1848220825, 5.01277399063, 9.70107460022, 8.30779933929, 2.92786860466, 2.37589669228, 2.42887616158, 2.56107378006, 2.54925966263, 3.33722281456, 3.19393587112, 2.1546959877, 2.28343367577, 6.05295038223, 10.4986152649, 10.2995796204, 8.13767910004, 9.78371810913, 9.40829563141, 13.5982465744, 8.78014850616, 8.65970611572, 5.50190877914, 3.8757109642, 2.88016963005, 2.18093037605, 1.86250567436, 0.904061198235, 0.0396548733115, 0.00127954024356, 0.000110535693238, 1.84924065252e-05, 9.22886192711e-06, 1.52474767674e-05],
        "dvar": [0.0021135811694, 0.145012050867, 12.5032129288, 122.80721283, 541.470153809, 504.916595459, 270.278686523, 42.5158081055, 246.248123169, 119.689506531, 17.3133983612, 15.3675508499, 12.0975637436, 16.9520549774, 10.5516214371, 24.9212665558, 29.2431621552, 12.5205135345, 12.6920995712, 62.3016052246, 220.552841187, 234.122268677, 209.096115112, 280.822692871, 322.454864502, 752.086120605, 278.50100708, 397.831329346, 119.550086975, 53.8362083435, 29.9175434113, 19.5586261749, 18.015203476, 3.30915784836, 0.00629790080711, 6.49628782412e-06, 4.68226204475e-08, 1.25249888239e-09, 1.51850698682e-10, 2.27532118147e-10],
        "dvar2": [0.00491700088605, 0.39475658536, 33.1471748352, 347.172576904, 1525.95043945, 1165.37304688, 561.06427002, 104.535377502, 652.98046875, 287.173828125, 45.6151275635, 31.0888195038, 30.2712421417, 42.6811981201, 26.6061630249, 55.1191749573, 78.9260406494, 32.4941596985, 30.9556026459, 144.981430054, 475.25970459, 495.695953369, 453.920196533, 607.308654785, 782.887634277, 1973.52954102, 694.963684082, 1054.41918945, 299.753387451, 139.362548828, 76.3508453369, 51.8922653198, 48.0504379272, 8.57882022858, 0.0161265749484, 1.66918052855e-05, 1.20384115121e-07, 3.20150350674e-09, 3.76115721901e-10, 5.56004131624e-10],
        "kurt": [23.9546794891, 57.0723457336, 1.47813844681, 3.19924783707, 21.3861274719, 6.90033340454, 7.06676006317, 11.785533905, 32.2333488464, 19.6617832184, 20.3962478638, 22.5273609161, 32.9421310425, 46.9935379028, 8.73334693909, 20.2180805206, 41.162612915, 53.1885375977, 26.3276233673, 18.8407859802, 19.002779007, 26.3448123932, 22.1141338348, 25.6908321381, 57.7931518555, 64.2946243286, 52.9756240845, 207.49848938, 48.2526817322, 50.2454338074, 43.8554344177, 65.9921646118, 196.220092773, 57.3911895752, 52.5096054077, 58.7341308594, 66.7433547974, 70.0104827881, 18.7661685944, 2.89107847214],
        "max": [0.537147521973, 5.25129032135, 33.0163764954, 123.018753052, 295.916809082, 269.965545654, 178.783935547, 108.284072876, 323.600921631, 182.330108643, 64.9622955322, 63.7578697205, 57.2762489319, 63.9192733765, 36.8144111633, 64.7509002686, 69.9334030151, 64.21043396, 48.7332229614, 117.103912354, 192.076721191, 228.032913208, 170.994033813, 222.047531128, 243.7474823, 319.755462646, 216.414520264, 393.243530273, 113.376548767, 94.5184936523, 60.9553642273, 58.8979797363, 81.4553146362, 22.220489502, 0.925424575806, 0.033053919673, 0.00309704407118, 0.000531510333531, 0.000189132799278, 0.000180024260771],
        "mean": [0.021020501852, 0.262301146984, 6.40726041794, 21.7585849762, 21.5512580872, 27.137342453, 17.778963089, 8.30888175964, 14.8881530762, 10.5469884872, 3.97187304497, 3.07205653191, 2.54361104965, 2.64969468117, 3.01540565491, 4.14788293839, 3.10635733604, 2.06165599823, 2.13437223434, 6.66728448868, 11.20291996, 10.2304811478, 7.72063398361, 8.02610778809, 6.45655345917, 7.38399171829, 5.03094053268, 4.41705942154, 2.89966511726, 1.94177091122, 1.46547949314, 1.00403785706, 0.90307110548, 0.430083662271, 0.0190964899957, 0.000634057912976, 6.22997540631e-05, 1.04848477349e-05, 1.5521678506e-05, 3.22727173625e-05],
        "median": [0.00472719129175, 0.183520466089, 5.14417171478, 17.110748291, 14.5836734772, 13.9797286987, 8.91997528076, 3.93410968781, 5.77206850052, 3.48831415176, 1.28043293953, 0.527477383614, 0.869613289833, 1.05812621117, 1.04000139236, 1.28396809101, 1.06203174591, 0.484405428171, 0.581405878067, 1.92011475563, 3.35598921776, 2.90799260139, 1.09939694405, 0.865870118141, 0.773212313652, 0.663988888264, 0.319464147091, 0.129573374987, 0.0881504863501, 0.0658686310053, 0.0543682724237, 0.0195157341659, 0.0155276600271, 0.00668273773044, 0.000289992603939, 2.9374497899e-05, 1.09697139123e-05, 1.58701254804e-06, 1.29343698063e-05, 2.96137695841e-05],
        "min": [2.33931539138e-22, 1.10352881129e-21, 1.73535076969e-20, 1.69938796165e-20, 1.40852734758e-20, 1.61400243678e-19, 2.31075127165e-19, 8.40880662201e-20, 5.31349547737e-19, 7.83155889004e-19, 9.2886737282e-19, 7.29653226598e-19, 2.09800589817e-18, 2.63929862216e-18, 1.14499043493e-18, 2.31410414486e-18, 2.01620518021e-18, 2.28247916889e-18, 3.54223470996e-18, 5.78919350257e-18, 6.91611376343e-18, 7.18945352889e-18, 7.17856286895e-18, 1.32710094695e-17, 1.42877004691e-17, 1.25640016563e-17, 1.99227393519e-17, 1.6067123131e-17, 1.38037253645e-17, 1.587959136e-17, 1.73400399428e-17, 1.71823181067e-17, 1.48317470841e-17, 8.36981792913e-18, 8.80355339205e-18, 6.4517660004e-18, 3.31065308976e-18, 1.17562455193e-18, 2.86343018847e-19, 3.15845669089e-20],
        "skew": [4.2592253685, 5.94960832596, 1.15653645992, 1.5686494112, 3.53387355804, 2.31547856331, 2.39476418495, 2.90407562256, 3.8187353611, 3.8966999054, 3.70364570618, 4.17993021011, 4.47963857651, 5.59346818924, 2.60226273537, 3.86264777184, 5.20022201538, 5.50716876984, 4.27080154419, 3.65758776665, 3.80755329132, 4.24979543686, 4.18821811676, 4.46102905273, 6.43468999863, 7.04819393158, 6.29095172882, 11.2873344421, 6.25297880173, 6.05975627899, 5.90077161789, 6.98672437668, 10.9831705093, 6.6603937149, 6.46177244186, 6.63809204102, 6.81606531143, 6.8092417717, 3.11621713638, 1.23792183399],
        "var": [0.00228480272926, 0.132998242974, 29.3684177399, 390.104248047, 667.850463867, 1208.17126465, 584.234069824, 143.121322632, 501.548431396, 393.565307617, 44.7023010254, 44.9415245056, 20.238817215, 23.2993793488, 20.6651115417, 54.7672042847, 34.0255432129, 17.0953083038, 17.5110836029, 141.054504395, 437.641723633, 387.020965576, 314.144012451, 389.74017334, 325.926513672, 591.918518066, 254.237335205, 299.172058105, 100.922683716, 43.0648612976, 24.7865161896, 14.4377288818, 13.2807102203, 2.57613396645, 0.00502962665632, 5.1842753237e-06, 3.81150471185e-08, 1.04338382378e-09, 2.46192843889e-10, 6.71120936602e-10]
    },
    "gfcc": {
        "dmean": [28.2311439514, 17.9907474518, 9.78363704681, 11.6279535294, 10.2308568954, 9.61552429199, 7.77475404739, 7.73230409622, 6.26140737534, 6.71349382401, 5.39503765106, 5.80019807816, 5.54475784302],
        "dmean2": [28.1312065125, 19.4337863922, 13.4235429764, 13.0013217926, 12.2164402008, 11.7482624054, 10.7100982666, 10.937286377, 9.392619133, 9.82348537445, 7.89531850815, 8.40256595612, 8.04150009155],
        "dvar": [951.66583252, 305.494293213, 86.7242736816, 93.5051574707, 81.5198440552, 65.4332733154, 41.6128425598, 41.6863822937, 27.408662796, 32.1677627563, 19.3550720215, 23.0127620697, 20.6213741302],
        "dvar2": [1039.78198242, 452.591278076, 133.13482666, 123.457206726, 105.782226562, 96.3328933716, 71.6016464233, 84.2973709106, 56.9037322998, 62.7517204285, 39.5359916687, 48.3182220459, 41.2164840698],
        "kurt": [4.5813331604, -0.240130662918, 2.6175661087, 1.64970588684, -0.386570930481, 0.610557794571, 0.648338794708, 0.560415029526, 1.05369186401, 0.535528659821, 1.35386419296, 1.04638433456, 0.928753137589],
        "max": [122.016075134, 275.979980469, 95.3638763428, 202.477554321, 53.565738678, 103.365028381, 36.0114898682, 34.489982605, 33.3399658203, 19.2456474304, 34.5712051392, 8.06908607483, 49.5404891968],
        "mean": [-148.811172485, 170.391769409, -98.1793670654, 59.3574447632, -43.2406082153, -8.76558303833, -40.2143325806, -17.3380527496, -17.3011646271, -35.7298431396, -4.90289306641, -22.6032066345, 1.80341720581],
        "median": [-111.727828979, 172.929641724, -112.34526062, 61.4705276489, -49.6303672791, -8.11953163147, -41.3132705688, -17.8443851471, -16.3417053223, -34.0324478149, -2.10423469543, -22.9554843903, 1.88268852234],
        "min": [-1264.91162109, 3.0517578125e-05, -176.874633789, -67.8377151489, -122.791275024, -69.7304992676, -110.839431763, -67.9697189331, -82.0185775757, -90.2942962646, -64.6226654053, -73.7149810791, -43.9888725281],
        "skew": [-1.47659766674, -0.235558182001, 1.69305872917, -0.551680326462, 0.558313548565, 0.3089017272, 0.0363279618323, -0.0900650843978, -0.387018918991, -0.527400195599, -0.993203639984, -0.318428367376, -0.100979059935],
        "var": [24128.1660156, 1965.5534668, 2476.43969727, 1053.10888672, 935.310058594, 737.146484375, 401.843078613, 225.91015625, 232.543792725, 246.172531128, 220.354675293, 140.154373169, 152.713180542]
    },
    "melbands": {
        "dmean": [0.000170207495103, 0.00102131487802, 0.00125467474572, 0.000798655673862, 0.000450632476714, 7.41119074519e-05, 9.32447437663e-05, 5.10167774337e-05, 1.38546538437e-05, 9.37814547797e-06, 7.65077038523e-06, 6.36720596958e-06, 6.15046383245e-06, 5.64574293094e-06, 5.49982905795e-06, 3.10583777718e-06, 2.60400815932e-06, 2.1720420591e-06, 4.52544827567e-06, 5.25155928699e-06, 1.02969206637e-05, 8.28200973046e-06, 5.68588939132e-06, 5.67389270145e-06, 5.41464578419e-06, 4.31887292507e-06, 5.07224785906e-06, 6.02081217949e-06, 3.75457670998e-06, 3.13210694003e-06, 2.91088690574e-06, 2.21193022298e-06, 1.36438370646e-06, 1.31096601308e-06, 1.07312314412e-06, 8.76332990174e-07, 7.54379186674e-07, 7.86359805716e-07, 7.63360901601e-07, 3.41858481079e-07],
        "dmean2": [0.000269378419034, 0.00165402737912, 0.00209770281799, 0.00130379258189, 0.000662477628794, 0.000117439354653, 0.00014613919484, 8.19936467451e-05, 2.18155109906e-05, 1.39304074764e-05, 1.2124954992e-05, 1.02981357486e-05, 9.97330153041e-06, 8.91193940333e-06, 8.70316944201e-06, 5.0189241847e-06, 4.35205402027e-06, 3.4728141145e-06, 6.96846336723e-06, 8.12923190097e-06, 1.58472594194e-05, 1.27842940856e-05, 8.94588720257e-06, 8.49395655678e-06, 8.24601102067e-06, 6.42334771328e-06, 8.0057507148e-06, 9.82925394055e-06, 5.93361073697e-06, 5.19833201906e-06, 4.74777561976e-06, 3.51593894266e-06, 2.19704816118e-06, 2.15480872612e-06, 1.72080683569e-06, 1.45081924074e-06, 1.27206067191e-06, 1.30870148496e-06, 1.28259148369e-06, 5.71750376821e-07],
        "dvar": [1.59302473435e-07, 1.70039493241e-06, 3.52600750375e-06, 1.96836617761e-06, 6.21794981726e-07, 2.38458675028e-08, 5.27212904444e-08, 1.06146327283e-08, 1.05797015593e-09, 4.86150397716e-10, 3.04900604764e-10, 2.79187700736e-10, 1.71954256389e-10, 1.88046814231e-10, 2.02673738903e-10, 7.90715132259e-11, 4.99387996233e-11, 2.98000131516e-11, 1.18420703799e-10, 1.2089344803e-10, 5.09623399036e-10, 3.28056110055e-10, 2.54126941712e-10, 2.32511204734e-10, 1.97277041925e-10, 1.54208132375e-10, 2.30743979479e-10, 4.29961344306e-10, 1.21951712617e-10, 1.56745894042e-10, 1.20808904547e-10, 5.54982726442e-11, 1.82605111587e-11, 1.71859644571e-11, 1.08735902227e-11, 8.79055595676e-12, 6.77605150809e-12, 9.82589183629e-12, 7.13153364487e-12, 1.36092049088e-12],
        "dvar2": [3.75164461275e-07, 4.50500238003e-06, 1.01700525192e-05, 5.17901025887e-06, 1.27343969325e-06, 5.85609036818e-08, 1.37555787205e-07, 2.60177976941e-08, 2.7816782211e-09, 9.7981611713e-10, 7.70983887843e-10, 7.15969894483e-10, 4.48585779633e-10, 4.53550780266e-10, 5.18648513026e-10, 2.1349090551e-10, 1.30948821231e-10, 7.46186445966e-11, 2.96320162851e-10, 2.8037552835e-10, 1.11228459776e-09, 6.80652811891e-10, 6.17698892036e-10, 5.30850918778e-10, 4.32341190626e-10, 3.60909913066e-10, 5.97043137152e-10, 1.13667320001e-09, 2.98720631564e-10, 4.14987211261e-10, 3.21165094519e-10, 1.40382219738e-10, 4.68030995904e-11, 4.49286267912e-11, 2.76991624082e-11, 2.3597554466e-11, 1.77517670702e-11, 2.64069443395e-11, 1.87978747151e-11, 3.5194458025e-12],
        "kurt": [30.7406692505, 0.847470521927, 3.31785392761, 9.65058898926, 8.61974334717, 12.1043052673, 24.6198348999, 18.9478149414, 18.0998306274, 20.9004993439, 35.4760017395, 58.316822052, 11.7390136719, 25.7220191956, 41.0436782837, 54.9782676697, 61.8413772583, 26.0803070068, 89.3004074097, 40.5166931152, 22.9087581635, 27.432888031, 34.8725242615, 23.4190139771, 25.4227485657, 62.7135620117, 54.0654602051, 82.0822753906, 44.5599746704, 185.699188232, 211.161300659, 61.513092041, 53.5330619812, 54.1289634705, 45.2839698792, 51.0388641357, 79.9643096924, 218.343795776, 107.502922058, 54.1187477112],
        "max": [0.0048118494451, 0.0121237440035, 0.0195118002594, 0.0161064714193, 0.009281815961, 0.0026326298248, 0.00452833995223, 0.00166775449179, 0.000485363823827, 0.000342829705914, 0.000283693661913, 0.000283795438008, 0.000150498541188, 0.000204725860385, 0.000225920928642, 0.000140507530887, 0.000131729975692, 6.44046231173e-05, 0.0002433378977, 0.000234426392126, 0.000296611338854, 0.000267019873718, 0.000188474281458, 0.000175150911673, 0.000172480606125, 0.000196747248992, 0.000189767990378, 0.000255560182268, 0.00012351910118, 0.000227260403335, 0.00021683423256, 8.57753766468e-05, 5.653559856e-05, 5.21992078575e-05, 3.61314341717e-05, 2.95203371934e-05, 3.80182027584e-05, 6.09887138125e-05, 4.29434549005e-05, 1.17479921755e-05],
        "mean": [0.000181940864422, 0.00261096796021, 0.0035572159104, 0.00171018764377, 0.000837561441585, 0.000191778119188, 0.000226016010856, 0.000100186014606, 2.90325060632e-05, 1.71467690961e-05, 1.20074219012e-05, 1.0020235095e-05, 1.06326115201e-05, 1.04163018477e-05, 9.21617720451e-06, 4.88562682222e-06, 3.85602970709e-06, 2.89453987534e-06, 6.57723376207e-06, 9.19455305848e-06, 1.56718360813e-05, 1.23027930385e-05, 7.22601635061e-06, 7.32877015253e-06, 6.46011130812e-06, 4.53167422165e-06, 4.70737995784e-06, 5.08854691361e-06, 3.44385330209e-06, 2.66538063443e-06, 2.42981877818e-06, 1.8227651708e-06, 1.13066255381e-06, 1.04150683455e-06, 8.78060291143e-07, 6.76368188124e-07, 5.84224210343e-07, 6.32663955002e-07, 6.05651393926e-07, 2.68409536375e-07],
        "median": [3.82189864467e-05, 0.00220651878044, 0.00296357134357, 0.00123152253218, 0.000411359418649, 8.34089296404e-05, 8.24367016321e-05, 3.38610843755e-05, 7.54688790039e-06, 2.81333859675e-06, 3.87412865166e-06, 3.72527392756e-06, 3.05804769596e-06, 3.14406906909e-06, 3.3278695355e-06, 1.34416131914e-06, 7.57807811169e-07, 6.27783606433e-07, 1.7420139784e-06, 2.68322082775e-06, 4.38024608229e-06, 3.58186889571e-06, 1.14757597203e-06, 7.27695464775e-07, 6.30975364402e-07, 5.10581287472e-07, 4.94908306337e-07, 3.74932170644e-07, 2.23657025344e-07, 8.96882426105e-08, 5.42080726973e-08, 5.13527851354e-08, 2.10687396418e-08, 3.58343470452e-08, 3.01340321585e-08, 1.1977615344e-08, 9.01088270666e-09, 8.15739831239e-09, 9.4008552054e-09, 2.66716160269e-09],
        "min": [3.62224653952e-24, 6.17018443299e-24, 2.9234609279e-24, 4.7918582604e-24, 7.2090692801e-24, 2.2805736056e-24, 9.63945191033e-24, 9.20802940329e-24, 7.19461734831e-24, 4.67301005414e-24, 1.14700580723e-23, 1.24079789787e-23, 1.35853611767e-24, 5.46349837941e-24, 5.77890074653e-24, 3.13044639373e-24, 4.53354260154e-24, 4.16815169657e-24, 9.34275185754e-24, 9.86656496494e-24, 6.37007586992e-24, 7.34871738184e-24, 7.34171071928e-24, 6.01342238834e-24, 1.15386795047e-23, 9.44946817194e-24, 9.62325028506e-24, 6.59685918067e-24, 1.24428048211e-23, 1.01233178903e-23, 9.03844245247e-24, 7.78258456883e-24, 7.15639703745e-24, 9.31443175105e-24, 7.29297647028e-24, 1.2320637877e-23, 9.28844272852e-24, 9.69236081124e-24, 6.64127717723e-24, 7.2080966146e-24],
        "skew": [4.71806907654, 0.983899474144, 1.55099081993, 2.39326810837, 2.5634803772, 2.89395356178, 3.61540842056, 3.7978541851, 3.57827115059, 4.05104207993, 4.65891122818, 6.10147953033, 2.95472311974, 4.15899085999, 5.0069437027, 5.75715446472, 5.89062738419, 4.41919279099, 6.7060956955, 5.15968513489, 4.10045576096, 4.35855579376, 5.07985210419, 4.35515499115, 4.49666404724, 6.58732318878, 6.36921548843, 7.93134641647, 5.88155651093, 11.262799263, 11.3865032196, 7.04675197601, 6.2338514328, 6.34467315674, 5.99453353882, 6.50576400757, 7.44079399109, 11.8310432434, 8.31803321838, 6.62019586563],
        "var": [1.7167543831e-07, 4.45900968771e-06, 9.69023039943e-06, 3.46510137206e-06, 1.3591024981e-06, 7.99015467123e-08, 1.22431444538e-07, 3.27791127575e-08, 2.69575184397e-09, 1.39891587203e-09, 4.76306993846e-10, 3.5808978005e-10, 2.96658753118e-10, 3.57080365276e-10, 2.78151002231e-10, 9.33916347035e-11, 6.50517278933e-11, 3.70147107409e-11, 1.72457506609e-10, 3.27742888384e-10, 9.25206022906e-10, 5.8195970265e-10, 2.98092106554e-10, 3.26326687894e-10, 2.64610666711e-10, 1.6647068446e-10, 1.97245192401e-10, 3.2680436135e-10, 1.15314979787e-10, 1.19193432901e-10, 9.01861432756e-11, 4.55701518187e-11, 1.4941502896e-11, 1.33915743078e-11, 9.00547778709e-12, 6.42023760544e-12, 5.09571248045e-12, 7.15120497541e-12, 5.35523621975e-12, 1.05602180646e-12]
    },
    "melbands128": {
        "dmean": [0.00010521774675, 0.000178798669367, 0.00021887125331, 0.000276326725725, 0.000959303870331, 0.00216445722617, 0.00192314654123, 0.0011603680905, 0.00140054908115, 0.000959986529779, 0.000849163974635, 0.000928244611714, 0.000320319755701, 8.33463345771e-05, 5.74941295781e-05, 0.000119884178275, 0.000124411541037, 0.000108935724711, 9.48740052991e-05, 7.13320114301e-05, 3.81348654628e-05, 1.58553648362e-05, 1.4593169908e-05, 1.51502408698e-05, 1.57107697305e-05, 5.63103367313e-06, 9.62787635217e-06, 1.13972591862e-05, 4.34312414654e-06, 7.00741566106e-06, 8.2974011093e-06, 9.36383185035e-06, 8.09386801848e-06, 5.08838365931e-06, 5.18587921761e-06, 8.66058780957e-06, 7.31978889235e-06, 4.6518111958e-06, 9.23906918615e-06, 4.17246155848e-06, 2.62975981968e-06, 2.20850233745e-06, 3.00336046166e-06, 3.84899658457e-06, 2.32088632401e-06, 2.36767118622e-06, 2.53857047028e-06, 3.95116239815e-06, 7.00912505636e-06, 7.99896315584e-06, 6.23925370746e-06, 4.10365555581e-06, 1.01691102827e-05, 1.37114056997e-05, 2.14121591853e-05, 4.34442654296e-06, 7.55901010052e-06, 7.52670075599e-06, 6.6482184593e-06, 4.22541324951e-06, 5.69540998185e-06, 8.76187550602e-06, 7.02430361343e-06, 5.05710841026e-06, 4.11075734519e-06, 4.04923139286e-06, 6.12259100308e-06, 3.58860279448e-06, 6.11415271123e-06, 6.25918755759e-06, 5.42612224308e-06, 7.16164049663e-06, 5.28972486791e-06, 2.98520376418e-06, 2.59149396697e-06, 2.94671940537e-06, 3.62561149814e-06, 4.13812176703e-06, 2.48559695137e-06, 2.38356528826e-06, 2.92206118502e-06, 1.96942460207e-06, 1.23998620438e-06, 1.48318383708e-06, 1.4487527551e-06, 1.30408341192e-06, 1.38143468575e-06, 1.20382105706e-06, 1.10276880605e-06, 9.89894942904e-07, 9.50037588154e-07, 8.26169070933e-07, 8.93521189482e-07, 7.3113920962e-07, 7.41674170968e-07, 7.54791813051e-07, 8.19821309506e-07, 8.92699233646e-07, 7.73801957621e-07, 7.64117828567e-07, 6.41492363229e-07, 2.5622628641e-07, 3.12420418425e-08, 1.01382002793e-09, 7.41224356199e-12, 5.38897268823e-12, 5.09345994201e-12, 4.83501476703e-12, 4.60401768793e-12, 4.3959258976e-12, 4.20691996864e-12, 4.03363020068e-12, 3.8748652724e-12, 3.72908605037e-12, 3.59513113724e-12, 3.47258962037e-12, 3.36018821274e-12, 3.25750060606e-12, 3.16402828417e-12, 3.07959061897e-12, 3.00382245119e-12, 2.93656895675e-12, 2.87762955825e-12, 2.82710573701e-12, 2.78507013458e-12, 2.75168494761e-12, 2.72724204331e-12, 2.71221023071e-12],
        "dmean2": [0.000158164111781, 0.000280475826003, 0.000357239419827, 0.000479834765429, 0.001618027105, 0.00345986406319, 0.0031926734373, 0.0019736753311, 0.00243632029742, 0.00162136706058, 0.00132343883161, 0.00136187183671, 0.00048868713202, 0.000130159794935, 9.55327413976e-05, 0.000191698767594, 0.000197153261979, 0.000167532882188, 0.000155802146764, 0.000113381669507, 6.29259593552e-05, 2.65387661784e-05, 2.37144631683e-05, 2.24833511311e-05, 2.34914987232e-05, 8.98716825759e-06, 1.56252790475e-05, 1.84301370609e-05, 7.52893674871e-06, 1.17182471513e-05, 1.34611482281e-05, 1.55222860485e-05, 1.32293062052e-05, 8.43580528453e-06, 8.74996294442e-06, 1.36995749926e-05, 1.13374671855e-05, 7.7694094216e-06, 1.51332360474e-05, 6.97239693181e-06, 4.33028162661e-06, 3.69630333807e-06, 5.14497332915e-06, 6.51791879136e-06, 3.99010195906e-06, 3.97529447582e-06, 4.14950363847e-06, 6.47141314403e-06, 1.14008262244e-05, 1.29244472191e-05, 1.01503628684e-05, 6.77652769809e-06, 1.6790247173e-05, 2.17054712266e-05, 3.43030442309e-05, 7.06451510268e-06, 1.28535111799e-05, 1.28887859319e-05, 9.99827716441e-06, 6.52055359751e-06, 9.00788472791e-06, 1.45393951243e-05, 1.09121256173e-05, 8.10981509858e-06, 6.45092814011e-06, 6.48484001431e-06, 9.57076190389e-06, 5.73490433453e-06, 9.99756321107e-06, 1.04018563434e-05, 9.15820055525e-06, 1.20630647871e-05, 8.53743676998e-06, 4.67869404019e-06, 4.24994505011e-06, 4.87407760374e-06, 6.05931563769e-06, 7.03695832271e-06, 4.08319965572e-06, 3.83369479096e-06, 4.7372300287e-06, 3.16801038025e-06, 2.01299894798e-06, 2.43379372478e-06, 2.44374450631e-06, 2.16606053982e-06, 2.29799911722e-06, 2.00861063604e-06, 1.83371832918e-06, 1.59980129411e-06, 1.56349199187e-06, 1.43032968936e-06, 1.56252644956e-06, 1.23891720705e-06, 1.25600649881e-06, 1.25716928778e-06, 1.38094731028e-06, 1.49277070705e-06, 1.30196519876e-06, 1.30176579205e-06, 1.07131950244e-06, 4.32929425642e-07, 5.12608124836e-08, 1.67945668483e-09, 1.29000074511e-11, 9.75938947712e-12, 9.22294272204e-12, 8.76166760672e-12, 8.34825264473e-12, 7.97381431716e-12, 7.63147964961e-12, 7.31739148441e-12, 7.02897419089e-12, 6.76449608134e-12, 6.52104021823e-12, 6.29722359327e-12, 6.0919958314e-12, 5.90458975117e-12, 5.73404301471e-12, 5.58000087109e-12, 5.44176856354e-12, 5.31916958396e-12, 5.2117832619e-12, 5.11976442144e-12, 5.04322278383e-12, 4.98245498678e-12, 4.93795195705e-12, 4.91059276575e-12],
        "dvar": [6.3992949606e-08, 1.92146657696e-07, 3.41811016824e-07, 4.94799166972e-07, 1.84808402537e-06, 7.6041092143e-06, 7.28824852558e-06, 4.71140720038e-06, 9.01628209249e-06, 3.39972075381e-06, 2.41661587097e-06, 2.85261057797e-06, 2.98032261981e-07, 7.46246087147e-08, 2.34342110161e-08, 6.03270464694e-08, 9.84554944239e-08, 9.28603753891e-08, 6.36777741647e-08, 2.47944527132e-08, 5.32486321703e-09, 1.63929325669e-09, 1.81622672457e-09, 1.52972712275e-09, 1.85907211847e-09, 2.5602112097e-10, 6.54985898851e-10, 7.85081555321e-10, 2.11443709763e-10, 4.51577636396e-10, 5.52852041924e-10, 6.42338293666e-10, 3.20037635282e-10, 9.82948375472e-11, 1.95068794451e-10, 5.92893567575e-10, 2.75006711847e-10, 2.31290500641e-10, 6.36668218146e-10, 1.5153403532e-10, 7.49212428208e-11, 4.16183094931e-11, 8.79551084743e-11, 1.01802462293e-10, 7.11896722128e-11, 4.71037479854e-11, 3.88109162863e-11, 2.0947849011e-10, 2.56447030278e-10, 2.88888690747e-10, 3.02034203203e-10, 1.01553633558e-10, 7.34807215075e-10, 1.08969977486e-09, 2.72978506466e-09, 1.20328524922e-10, 6.30228980114e-10, 6.40443031941e-10, 3.44649808692e-10, 1.61388610809e-10, 2.39191166873e-10, 7.96196164554e-10, 3.51440432311e-10, 2.03774982999e-10, 1.61637897511e-10, 1.84393222913e-10, 3.85488585497e-10, 1.11673843783e-10, 4.36356784039e-10, 4.66859717552e-10, 4.22689605539e-10, 8.24433743496e-10, 2.61370869392e-10, 7.64476398851e-11, 7.03816865899e-11, 1.73899825096e-10, 3.29486438133e-10, 2.67521116371e-10, 1.00474871478e-10, 7.15487460945e-11, 1.23008395136e-10, 4.54085311019e-11, 1.66448799188e-11, 2.58611899256e-11, 2.46051512498e-11, 1.81495356938e-11, 2.27058909869e-11, 1.60323629372e-11, 1.49894732043e-11, 1.08085918687e-11, 1.03515989183e-11, 1.1091648433e-11, 1.07245523226e-11, 6.84378768934e-12, 6.94764515016e-12, 9.2098750501e-12, 1.30324960892e-11, 1.19277218311e-11, 8.22609948908e-12, 7.34818542819e-12, 5.25255446776e-12, 9.16795719202e-13, 1.16731795806e-14, 1.17298578374e-17, 2.25818060551e-22, 1.32409053386e-22, 1.14881851493e-22, 1.01284375976e-22, 9.02912269196e-23, 8.1148726614e-23, 7.34162804666e-23, 6.68048750853e-23, 6.1097744115e-23, 5.61457108033e-23, 5.18288178053e-23, 4.80510449717e-23, 4.47431397814e-23, 4.18471304241e-23, 3.93131798234e-23, 3.71045459936e-23, 3.51848908461e-23, 3.35306274397e-23, 3.21205575043e-23, 3.09400965794e-23, 2.99781974569e-23, 2.92262015995e-23, 2.86822567618e-23, 2.83510929538e-23],
        "dvar2": [1.4649788227e-07, 4.71674496794e-07, 8.55516873344e-07, 1.38004588734e-06, 5.1720362535e-06, 1.97750468942e-05, 2.03724739549e-05, 1.30584940052e-05, 2.53744492511e-05, 9.66031348071e-06, 5.81938866162e-06, 5.78060507905e-06, 6.57476618926e-07, 1.58582267318e-07, 5.56432553367e-08, 1.56643238824e-07, 2.66077705646e-07, 2.34228949125e-07, 1.5840689116e-07, 5.89046962318e-08, 1.39681137767e-08, 4.40918812572e-09, 4.61030102983e-09, 3.03073677266e-09, 3.84511000817e-09, 5.76133973862e-10, 1.54590762413e-09, 2.03012939792e-09, 6.10976491622e-10, 1.27609012246e-09, 1.31576105566e-09, 1.80329784438e-09, 8.27999502295e-10, 2.55850479691e-10, 5.18893206181e-10, 1.39354694451e-09, 6.50565157301e-10, 6.31943664064e-10, 1.74051706381e-09, 4.17683332365e-10, 2.03052200054e-10, 1.12983018774e-10, 2.50795356704e-10, 2.60667376573e-10, 1.94757363015e-10, 1.25298021958e-10, 1.00867841857e-10, 5.18657561344e-10, 6.78781031382e-10, 7.44981853984e-10, 7.14995063156e-10, 2.64669813843e-10, 1.9695680642e-09, 2.53452148158e-09, 6.49609743775e-09, 2.87057322357e-10, 1.70367331354e-09, 1.76397407792e-09, 7.76581798867e-10, 3.84217713201e-10, 5.9237692529e-10, 2.02692151952e-09, 8.01327837419e-10, 4.89067619736e-10, 3.84872217429e-10, 4.51509551969e-10, 9.57590784445e-10, 2.88370438639e-10, 1.14478915236e-09, 1.26318300264e-09, 1.14882492408e-09, 2.163087931e-09, 6.44997666388e-10, 1.79838713366e-10, 1.83400919451e-10, 4.78071582322e-10, 8.88275064614e-10, 7.36084360131e-10, 2.72280697988e-10, 1.77472342378e-10, 3.13579606726e-10, 1.15899956299e-10, 4.16075195131e-11, 6.80069819903e-11, 6.53172030352e-11, 4.77409327349e-11, 5.97936283819e-11, 4.24443674651e-11, 3.98301912286e-11, 2.72141024993e-11, 2.71135110891e-11, 3.10578056328e-11, 2.9548186814e-11, 1.81337514449e-11, 1.76392962736e-11, 2.48857184859e-11, 3.55841120458e-11, 3.18309545388e-11, 2.20718859856e-11, 1.96142199704e-11, 1.37104754633e-11, 2.39947254774e-12, 2.93810487821e-14, 3.05929374656e-17, 6.53129523112e-22, 4.12925694119e-22, 3.56546196498e-22, 3.13063072686e-22, 2.7817646277e-22, 2.49356029132e-22, 2.25128835934e-22, 2.04498507675e-22, 1.86757152134e-22, 1.71403015911e-22, 1.58055476772e-22, 1.46411713107e-22, 1.3623370349e-22, 1.27336198138e-22, 1.19561336517e-22, 1.12791887587e-22, 1.06913977697e-22, 1.01851238801e-22, 9.75394513107e-23, 9.39316117379e-23, 9.09931427313e-23, 8.86963521177e-23, 8.70353518392e-23, 8.60248462631e-23],
        "kurt": [37.005115509, 35.9504928589, 54.1395874023, 88.5892868042, 9.4819688797, 0.158133745193, 3.76928853989, 9.6843957901, 26.039648056, 20.7221546173, 9.12037849426, 10.5476932526, 8.03561782837, 69.1532058716, 28.2254257202, 7.42992305756, 38.8472633362, 20.491985321, 55.1192359924, 18.4953727722, 9.92294883728, 31.3393363953, 44.5447044373, 24.2354106903, 33.876739502, 42.1363677979, 59.5177726746, 47.3191871643, 251.557434082, 164.008666992, 65.6379013062, 37.7544822693, 13.1210842133, 14.0521316528, 17.9539413452, 54.1908988953, 22.7606658936, 70.7788696289, 52.0270271301, 53.2672805786, 125.200775146, 38.7631263733, 173.840301514, 41.6297302246, 169.055618286, 36.6642074585, 33.0382003784, 295.526824951, 47.0539360046, 23.6687908173, 116.602493286, 30.5009918213, 46.6625747681, 32.3142166138, 41.7587966919, 40.7267189026, 103.246337891, 73.0625991821, 48.9925308228, 42.836566925, 23.6857032776, 55.3051109314, 36.7018013, 34.8999633789, 40.2969818115, 96.1720733643, 81.6628723145, 44.0797538757, 74.4843521118, 128.082183838, 110.177398682, 155.964157104, 52.7730293274, 41.0968551636, 82.1538238525, 264.077270508, 466.905334473, 156.303771973, 198.854888916, 83.7476882935, 104.138389587, 62.7142333984, 66.3456192017, 60.9974784851, 55.0356521606, 59.3789176941, 63.2984848022, 58.7237892151, 67.6166915894, 64.6805953979, 51.2230377197, 85.1271591187, 59.9543685913, 77.7823867798, 77.5553359985, 216.484512329, 230.066345215, 210.613510132, 153.160507202, 62.3159408569, 68.9067764282, 86.6124038696, 81.8648986816, 55.0943145752, 36.1724128723, 65.2857131958, 52, 57, 42.25, 43.6666679382, 52, 41, 33, 56, 47, 39, 33, 28, 24, 21, 18, 16, inf, inf, inf, inf, inf, inf],
        "max": [0.00343472859822, 0.00587678002194, 0.00731695257127, 0.00956821069121, 0.0168586764485, 0.0244403779507, 0.0318726412952, 0.0225672256202, 0.0398788265884, 0.0224182102829, 0.0181929133832, 0.0204394105822, 0.00549020012841, 0.00717432145029, 0.00289969379082, 0.00318822124973, 0.00652136560529, 0.00536159705371, 0.0057419212535, 0.00222854269668, 0.000776441185735, 0.000645726046059, 0.000781965034548, 0.000664474209771, 0.000754120876081, 0.00026444948162, 0.000427544815466, 0.000505001749843, 0.000298760423902, 0.000444261357188, 0.000376661948394, 0.000375865463866, 0.000172672560439, 0.000105819031887, 0.000147734812344, 0.000439874187578, 0.000238557389821, 0.000213446837733, 0.000368292501662, 0.000175540626515, 0.000168765531271, 8.58394632814e-05, 0.000202626557439, 0.000134016634547, 0.000157974514877, 7.14947818778e-05, 7.80486516305e-05, 0.000369231303921, 0.000280793348793, 0.000218789136852, 0.000480942690047, 0.000120869895909, 0.000406834878959, 0.00044565810822, 0.000818518397864, 0.00013971037697, 0.000400613498641, 0.000338685989846, 0.000269690499408, 0.000173313776031, 0.000157103626407, 0.000388705811929, 0.000255221006228, 0.000163156437338, 0.000136314702104, 0.000231817713939, 0.000251964200288, 0.000112330504635, 0.000296929792967, 0.000355429103365, 0.000294689962175, 0.000497844826896, 0.000184385891771, 0.000106074803625, 0.000120848315419, 0.000272884266451, 0.000421096716309, 0.00027516373666, 0.000189289727132, 0.000122077093692, 0.000152577893459, 7.92003993411e-05, 5.54636026209e-05, 5.69688418182e-05, 5.9083555243e-05, 4.9070953537e-05, 5.23274320585e-05, 5.01501417602e-05, 4.23404162575e-05, 4.33699024143e-05, 3.53679461114e-05, 4.14165588154e-05, 3.49407782778e-05, 3.48340472556e-05, 3.84305058105e-05, 5.88406692259e-05, 6.72683527227e-05, 6.67201893521e-05, 5.02181355841e-05, 3.15943107125e-05, 2.64444897766e-05, 1.22496685435e-05, 1.61689877132e-06, 3.9033839272e-08, 1.7343437797e-10, 1.52147974775e-10, 1.37560574043e-10, 1.26051794003e-10, 1.16590834209e-10, 1.08612070726e-10, 1.01747166248e-10, 9.57714185734e-11, 9.05252955929e-11, 8.58846258001e-11, 8.17589190794e-11, 7.80821310387e-11, 7.47979594928e-11, 7.18667833577e-11, 6.92595703011e-11, 6.69414593202e-11, 6.4894520313e-11, 6.31013782892e-11, 6.15491962952e-11, 6.02341579392e-11, 5.91523080518e-11, 5.82978734731e-11, 5.76726964796e-11, 5.72910226204e-11],
        "mean": [0.000104627826659, 0.00016599263472, 0.00017996650422, 0.000274929770967, 0.00156732380856, 0.00571730360389, 0.00509639689699, 0.00213420530781, 0.00235787895508, 0.00155799940694, 0.00145696045365, 0.00160479568876, 0.000517656386364, 0.000151075146277, 0.000112631343654, 0.000284226582153, 0.000276381702861, 0.000213295294088, 0.000169478051248, 0.000121684977785, 6.39307327219e-05, 2.72274373856e-05, 2.57571173279e-05, 2.69524443866e-05, 2.55818940786e-05, 7.39340794098e-06, 1.28475867314e-05, 1.72937998286e-05, 5.10490235683e-06, 8.95794528333e-06, 1.11754825411e-05, 1.33192061185e-05, 1.21863085951e-05, 7.3993614933e-06, 7.08073184796e-06, 1.39903295349e-05, 1.2594627151e-05, 5.39116126674e-06, 1.22573392218e-05, 5.57154589842e-06, 3.3826111121e-06, 2.95214431389e-06, 3.72265776605e-06, 5.02195280205e-06, 2.41250586441e-06, 2.60652109318e-06, 2.85495775643e-06, 4.40460189566e-06, 9.34568652156e-06, 1.15746443043e-05, 9.05495198822e-06, 5.3718486015e-06, 1.24220669022e-05, 1.89999445865e-05, 2.79716987279e-05, 4.83002349938e-06, 7.86745749792e-06, 7.96505719336e-06, 7.61960563977e-06, 5.13562872584e-06, 6.83401140122e-06, 9.35787556955e-06, 7.92355695012e-06, 5.3698827287e-06, 4.35911852037e-06, 3.97896337745e-06, 5.86054375162e-06, 3.33613115799e-06, 5.27676684214e-06, 5.24786310052e-06, 4.3442310016e-06, 5.82386246606e-06, 4.60102137367e-06, 2.85106671072e-06, 2.26225529332e-06, 2.48764695243e-06, 2.86460476673e-06, 3.12860856866e-06, 2.14523038267e-06, 2.01066336558e-06, 2.32000911637e-06, 1.57726594807e-06, 1.01717239431e-06, 1.17520778531e-06, 1.13465239338e-06, 1.0234898582e-06, 1.08116364572e-06, 9.20884701827e-07, 8.82399831426e-07, 8.27365852274e-07, 7.52495623146e-07, 5.97481175646e-07, 6.24536710347e-07, 5.5782555819e-07, 5.86798819313e-07, 5.99568011239e-07, 6.37648668089e-07, 6.9582983997e-07, 5.99372810939e-07, 5.87026420362e-07, 4.94042865284e-07, 1.98113141892e-07, 2.46226967704e-08, 7.86244125361e-10, 6.47354045369e-12, 4.3200074594e-12, 4.08502485311e-12, 3.88055559908e-12, 3.69809174602e-12, 3.53280404063e-12, 3.38191605796e-12, 3.24358747326e-12, 3.11644460238e-12, 2.99946699422e-12, 2.89187098747e-12, 2.79304812785e-12, 2.70243311236e-12, 2.61965102388e-12, 2.54428205934e-12, 2.47617377991e-12, 2.41502477738e-12, 2.36077216803e-12, 2.31325288785e-12, 2.27253740999e-12, 2.23866541624e-12, 2.2117672277e-12, 2.19209004247e-12, 2.17996974639e-12],
        "median": [7.45318175177e-06, 8.5813953774e-06, 1.6796442651e-05, 9.66300140135e-05, 0.001092919847, 0.00477374019101, 0.00381823070347, 0.00112396210898, 0.00138136860915, 0.000929752248339, 0.000524700910319, 0.000645513879135, 0.00022194047051, 1.59629562404e-05, 2.47947846219e-05, 9.76079463726e-05, 0.000111861678306, 1.9686507585e-05, 9.11880488275e-06, 2.93851808237e-05, 2.19335051952e-05, 5.86647729506e-06, 1.88155536307e-06, 2.14372312257e-06, 2.36611731452e-06, 5.20212552146e-07, 2.43654903898e-06, 4.34513003711e-06, 1.90929426935e-06, 2.1351270334e-06, 3.28643704961e-06, 2.44857574216e-06, 2.48911078415e-06, 2.34827211898e-06, 8.73649241839e-07, 3.36206448992e-06, 2.97955602946e-06, 1.20854315355e-06, 3.04306468024e-06, 1.16760929814e-06, 3.89092861042e-07, 2.74502554021e-07, 5.6022292938e-07, 8.19572846922e-07, 2.29607564961e-07, 2.53909320236e-07, 4.23081786494e-07, 4.98446524944e-07, 2.05289461519e-06, 2.42245801019e-06, 1.57898034558e-06, 1.24594589579e-06, 2.31619242186e-06, 4.4166108637e-06, 6.45160162094e-06, 9.5499285635e-07, 1.17533488719e-06, 7.90409842466e-07, 7.98697215032e-07, 3.60235247854e-07, 4.30333159329e-07, 6.72334294904e-07, 6.6555247713e-07, 4.43692101726e-07, 3.45189675954e-07, 3.74144832449e-07, 4.75297923686e-07, 2.56973578416e-07, 3.26375584336e-07, 3.84375539397e-07, 2.24285216177e-07, 2.9024010928e-07, 2.3070040811e-07, 1.48996349481e-07, 9.41994358072e-08, 4.959461819e-08, 3.93179320213e-08, 3.89675847146e-08, 3.23834932203e-08, 4.3308666875e-08, 5.39015694301e-08, 3.66495456205e-08, 1.16892096003e-08, 9.9177199786e-09, 1.2974913588e-08, 2.44751596767e-08, 2.99012015148e-08, 2.23031442204e-08, 2.29865584345e-08, 1.4539921267e-08, 9.34932131713e-09, 5.56319257328e-09, 6.16242257223e-09, 5.38801625538e-09, 4.7423172056e-09, 4.99930630227e-09, 5.63175994728e-09, 8.97984264725e-09, 6.30609875429e-09, 4.508023288e-09, 3.40831940449e-09, 1.3071104199e-09, 2.15867823616e-10, 1.34848581954e-11, 1.28515037154e-12, 8.39335762351e-13, 7.9647117894e-13, 7.49193513217e-13, 7.03256680321e-13, 6.7890203008e-13, 6.5102990273e-13, 6.25124951803e-13, 5.91009175193e-13, 5.57548690376e-13, 5.39186425542e-13, 5.2453289108e-13, 5.11469230684e-13, 4.88659134858e-13, 4.76685748166e-13, 4.63410776766e-13, 4.54169308498e-13, 4.45737251362e-13, 4.36594987593e-13, 4.28806404447e-13, 4.2247000169e-13, 4.1729965837e-13, 4.1348180305e-13, 4.11208610565e-13],
        "min": [1.1911469925e-23, 2.7632180345e-24, 1.39178916863e-24, 1.01470823251e-24, 4.67762173499e-24, 1.06576212701e-23, 3.33025164761e-24, 1.25731776935e-24, 7.36360387738e-25, 2.11501576185e-24, 7.8943338158e-24, 5.51769075701e-24, 1.09632520172e-23, 3.93683716878e-24, 8.43797868914e-25, 1.48880801592e-24, 3.28487025467e-24, 1.26763399924e-23, 1.54040853185e-23, 3.98163263528e-24, 5.55233752797e-24, 8.26994125835e-24, 7.79823556919e-24, 4.10924232518e-24, 3.17764216676e-24, 5.17120017047e-24, 6.20246067693e-24, 7.82011699298e-24, 1.61677799832e-23, 7.92298918818e-24, 5.14504943146e-24, 3.27728269466e-25, 9.50666827896e-25, 1.60587359374e-24, 3.45365986433e-24, 7.19504648864e-24, 5.21609621674e-24, 7.77805887381e-24, 3.60169237421e-24, 1.05130526484e-24, 4.20838360274e-24, 3.94899035988e-24, 3.28055577716e-24, 4.02797979118e-24, 4.52503394781e-24, 1.50726006413e-24, 4.07115414853e-24, 1.3783959079e-23, 4.35965438663e-24, 4.1828387089e-24, 1.03951033492e-23, 8.93610037179e-24, 3.36988401949e-24, 7.54893974592e-24, 6.55586326272e-24, 8.15859433044e-24, 5.59911106319e-24, 7.46912595497e-24, 5.46844848159e-24, 5.12731583832e-24, 4.90348010633e-24, 4.33365708107e-24, 1.16372271644e-23, 1.59638057966e-23, 6.89879293113e-24, 7.31397121441e-24, 1.27847965339e-23, 1.16396757887e-23, 8.56185765861e-24, 6.28144537506e-24, 2.66872630312e-24, 7.40252479533e-24, 1.16289906677e-23, 1.05978145694e-23, 1.11591253911e-23, 7.23235250971e-24, 8.18388521106e-24, 9.90458727171e-24, 9.94755179206e-24, 5.52480470466e-24, 7.25165199176e-24, 9.19300239191e-24, 5.63183853557e-24, 3.91469344874e-24, 1.07802291874e-23, 9.11265296441e-24, 8.89440433978e-24, 7.21953036456e-24, 4.50410152369e-24, 8.9060810589e-24, 1.10589021908e-23, 1.18938010184e-23, 9.1408500086e-24, 8.27864633844e-24, 6.53944982829e-24, 1.08581710114e-23, 7.59478913059e-24, 7.98332521452e-24, 7.976806068e-24, 4.072600525e-24, 6.64709423755e-24, 7.28671764786e-24, 8.22499590828e-24, 8.50595897486e-24, 9.59893838082e-24, 1.07179636073e-23, 1.07501199444e-23, 1.03420453535e-23, 1.08986774412e-23, 9.78574695406e-24, 6.42933865099e-24, 1.00520301081e-23, 1.19788765116e-23, 9.80567515825e-24, 1.06254247011e-23, 5.54332794757e-24, 6.09174483774e-24, 8.65878736461e-24, 6.40382452273e-24, 9.24754265717e-24, 9.17535320687e-24, 8.65947682904e-24, 8.12474509786e-24, 8.62164858206e-24, 7.23317134733e-24, 9.49635806415e-24, 9.44374893038e-24, 9.54174359861e-24],
        "skew": [5.08985042572, 4.84789943695, 6.1988286972, 7.85449314117, 2.23378348351, 0.871813416481, 1.68302464485, 2.87544679642, 3.9090025425, 3.52516269684, 2.64896535873, 2.85560679436, 2.59977340698, 7.30708456039, 4.86250305176, 2.49363493919, 4.08091306686, 3.74327588081, 6.50607633591, 3.98835372925, 2.70199537277, 4.63935899734, 5.56182956696, 4.39628267288, 5.12258243561, 5.76671457291, 6.38095521927, 5.3096203804, 12.6190023422, 9.33828258514, 7.00398206711, 4.80257987976, 3.26595211029, 3.23518466949, 4.01222753525, 6.15463018417, 4.1884894371, 7.18269348145, 5.74785804749, 5.98550462723, 8.68897151947, 5.48082923889, 9.66642189026, 5.34165048599, 10.7236671448, 5.35456371307, 4.82849216461, 13.9507665634, 5.14261388779, 4.05965614319, 9.43457794189, 4.77835035324, 5.83829641342, 4.84044981003, 5.37396526337, 5.48662900925, 8.37533473969, 7.28013944626, 5.99542474747, 5.53954267502, 4.3844165802, 6.38059520721, 5.23743438721, 5.21805477142, 5.73827075958, 8.12026500702, 7.87745380402, 5.86989927292, 7.44182109833, 9.22484111786, 9.1278924942, 10.589632988, 6.38198232651, 5.74922800064, 7.55380582809, 13.2696456909, 18.2300395966, 10.3820419312, 11.3084955215, 7.92381191254, 8.97273731232, 7.17510461807, 7.04292678833, 6.9684214592, 6.57790374756, 6.73171138763, 7.14056158066, 6.69551420212, 7.33552598953, 6.96287345886, 6.49074554443, 8.30128669739, 7.07036542892, 7.62845134735, 7.44544219971, 11.8317041397, 12.7000303268, 11.4081687927, 9.8460559845, 7.01529455185, 7.35100078583, 8.11040115356, 7.69332838058, 6.64879560471, 5.0316028595, 6.33717441559, 6.02833557129, 5.80294275284, 5.6307349205, 5.49514389038, 5.3854932785, 5.29535675049, 5.22024250031, 5.15697431564, 5.10309362411, 5.05689048767, 5.01707220078, 4.982609272, 4.95301675797, 4.92735815048, 4.90521144867, 4.88612270355, 4.86992835999, 4.85646247864, 4.84563207626, 4.83709812164, 4.83080720901, 4.82707500458],
        "var": [7.48888524527e-08, 1.88344870367e-07, 2.88338583232e-07, 3.72258483594e-07, 2.6306588552e-06, 2.26791107707e-05, 2.34614471992e-05, 9.05045999389e-06, 1.02112280729e-05, 4.30166210208e-06, 4.91715127282e-06, 6.10774850429e-06, 5.83130884024e-07, 2.4401799692e-07, 7.98236854394e-08, 1.92512743524e-07, 1.80184855481e-07, 2.18603091184e-07, 2.35907975821e-07, 6.88951615757e-08, 9.24493548382e-09, 3.2303091313e-09, 4.29686020098e-09, 4.55917570363e-09, 4.70254013507e-09, 5.32715982438e-10, 9.86699610905e-10, 1.1870124883e-09, 1.56944179874e-10, 4.18297035898e-10, 7.48460737832e-10, 7.59770468761e-10, 5.15777587307e-10, 1.55903415178e-10, 3.16161374858e-10, 1.02114650069e-09, 6.37902786149e-10, 2.33569857899e-10, 6.5334493371e-10, 1.58277904672e-10, 7.66564312027e-11, 6.05206093574e-11, 8.46876041516e-11, 1.26892871211e-10, 6.01982977355e-11, 4.67753578925e-11, 4.16931142388e-11, 2.22385110327e-10, 3.46430079068e-10, 5.08276587485e-10, 8.11191613881e-10, 1.36498715109e-10, 1.0067700007e-09, 1.72627445671e-09, 4.15024903333e-09, 1.35040867377e-10, 5.09975117691e-10, 5.39748024053e-10, 4.35909891516e-10, 1.88731724693e-10, 3.01927927104e-10, 8.13685840928e-10, 4.6322898295e-10, 2.18953549735e-10, 1.68942082546e-10, 1.72524092235e-10, 3.62692958999e-10, 9.9482221072e-11, 3.49016593404e-10, 3.351448008e-10, 2.95257929217e-10, 6.19273798907e-10, 2.35292840767e-10, 8.08470027036e-11, 5.80400900951e-11, 1.29302887841e-10, 2.26251628543e-10, 1.8413741365e-10, 7.26968485409e-11, 5.98391544648e-11, 9.7155027079e-11, 3.65847352413e-11, 1.41410503099e-11, 2.01399487365e-11, 1.80947184319e-11, 1.38481309753e-11, 1.7389025983e-11, 1.18302477189e-11, 1.11549146656e-11, 9.12006581366e-12, 8.06968901423e-12, 7.08936945606e-12, 7.04040515123e-12, 5.01986950271e-12, 5.56241901498e-12, 6.6868056231e-12, 8.99506857888e-12, 8.56812797795e-12, 5.92513408129e-12, 5.34290884105e-12, 3.97800802715e-12, 6.8692236144e-13, 9.767116586e-15, 9.04440770691e-18, 2.01978974296e-22, 1.00570418992e-22, 8.82041155346e-23, 7.84091389079e-23, 7.03575007056e-23, 6.35789199212e-23, 5.77870400462e-23, 5.27882683035e-23, 4.8442556639e-23, 4.46463623256e-23, 4.1318375892e-23, 3.83948699991e-23, 3.58236472983e-23, 3.35637722195e-23, 3.15795882499e-23, 2.98454321666e-23, 2.83346657143e-23, 2.70303914926e-23, 2.59161286194e-23, 2.49817733643e-23, 2.4219233592e-23, 2.36227632398e-23, 2.31910701535e-23, 2.29276789636e-23]
    },
    "mfcc": {
        "dmean": [29.6981773376, 21.508228302, 11.059258461, 8.90860176086, 8.16690731049, 7.12322425842, 7.37234783173, 6.91882371902, 6.87021064758, 6.57941913605, 6.55319452286, 6.24930763245, 6.23283481598],
        "dmean2": [29.1089286804, 22.1176376343, 13.8428697586, 11.8006696701, 11.2726573944, 10.4026432037, 10.4032773972, 10.2120456696, 10.2908525467, 9.60467338562, 9.50892543793, 9.58883094788, 9.31859970093],
        "dvar": [879.001037598, 416.14440918, 92.1692352295, 53.6578979492, 48.6906929016, 35.1093826294, 35.0336456299, 34.0121116638, 31.4902324677, 27.7884979248, 28.2663993835, 26.4316539764, 25.8005065918],
        "dvar2": [1192.23706055, 572.317626953, 128.774047852, 87.8872146606, 83.3650894165, 72.4232635498, 70.7522506714, 69.1727981567, 65.8931884766, 56.7366943359, 59.8657455444, 57.5029945374, 55.4629249573],
        "kurt": [-0.231350660324, -0.397194623947, 0.868809938431, 2.28783130646, 1.5521273613, 0.952816009521, 1.42047595978, 0.83495759964, 0.631996154785, 0.69939661026, 0.0446605682373, 1.27576351166, 0.424173355103],
        "max": [-492.512908936, 303.357910156, 174.602523804, 185.212310791, 123.000778198, 67.0956954956, 70.3266067505, 79.6044311523, 54.5265808105, 35.8470153809, 22.8985843658, 36.4564666748, 60.3838996887],
        "mean": [-784.210998535, 168.337081909, 20.7982196808, 53.8110847473, 23.4984378815, 1.86126708984, -2.27082324028, 2.59192204475, -5.92800712585, -13.9031572342, -20.8353939056, -3.6376888752, 2.24688220024],
        "median": [-753.880249023, 169.265319824, 15.076333046, 53.3988952637, 20.5001831055, 0.662978172302, -4.275390625, 0.865062713623, -6.56597900391, -14.2825660706, -18.9081802368, -2.65277481079, 0.412134170532],
        "min": [-1264.91162109, 3.0517578125e-05, -76.7839584351, -43.911151886, -48.4979743958, -41.0466690063, -75.5762710571, -68.6614456177, -59.4258995056, -63.2548217773, -76.5009460449, -58.7589454651, -42.6071166992],
        "skew": [-0.706057429314, -0.0732899978757, 0.75430649519, -0.0283347256482, 0.903528988361, 0.63384270668, 0.364800065756, 0.430734395981, 0.0874205827713, 0.196201443672, -0.46744582057, -0.655880093575, 0.444758951664],
        "var": [24175.0273438, 3036.9831543, 1614.65917969, 610.136474609, 472.52532959, 299.347991943, 346.279815674, 303.672515869, 263.590942383, 165.265991211, 235.332809448, 181.569869995, 213.671157837]
    },
    "spectral_contrast_coeffs": {
        "dmean": [0.0441334061325, 0.0399056747556, 0.0320825167, 0.0291937477887, 0.0276643354446, 0.0333518087864],
        "dmean2": [0.0709019303322, 0.0605057813227, 0.0505317635834, 0.045159060508, 0.0420554280281, 0.0477260239422],
        "dvar": [0.00139047531411, 0.00112524582073, 0.000658334174659, 0.000525199400727, 0.000545216666069, 0.000898312719073],
        "dvar2": [0.00366435968317, 0.00263711251318, 0.00161950557958, 0.00122270954307, 0.00111602002289, 0.00191594881471],
        "kurt": [1.0267033577, -0.0791566371918, -0.0821902751923, 0.328605651855, 0.812000989914, 0.544281005859],
        "max": [-0.354225933552, -0.43136382103, -0.633556962013, -0.582213282585, -0.540729701519, -0.456712931395],
        "mean": [-0.56783503294, -0.711557626724, -0.783151626587, -0.77759718895, -0.765241086483, -0.741257250309],
        "median": [-0.561812996864, -0.710727095604, -0.785312235355, -0.77759462595, -0.767716765404, -0.741540849209],
        "min": [-0.969227015972, -0.973166227341, -0.96378660202, -0.968333542347, -0.968872904778, -0.963954627514],
        "skew": [-0.522933483124, -0.00648133503273, 0.119905792177, -0.041126742959, 0.20639179647, 0.101245425642],
        "var": [0.00617538252845, 0.00627797469497, 0.00242274580523, 0.0030951355584, 0.00332181877457, 0.00587307009846]
    },
    "spectral_contrast_valleys": {
        "dmean": [0.400644809008, 0.376015454531, 0.368059366941, 0.387391626835, 0.509449899197, 0.739352941513],
        "dmean2": [0.600279986858, 0.538056731224, 0.520822584629, 0.489681750536, 0.539416134357, 0.819686949253],
        "dvar": [0.281316697598, 0.285617142916, 0.28771802783, 0.290665239096, 0.381397426128, 0.489433377981],
        "dvar2": [0.304970085621, 0.286186486483, 0.306490123272, 0.28817653656, 0.406831681728, 0.681817233562],
        "kurt": [45.3962936401, 16.8373222351, 21.4808731079, 9.93196773529, 4.14021921158, 1.70209932327],
        "max": [-5.00111246109, -5.10135364532, -6.11424446106, -6.28235006332, -5.50987243652, -7.9181265831],
        "mean": [-7.21303510666, -8.18628883362, -9.03779220581, -9.47572612762, -9.4735584259, -12.9422292709],
        "median": [-6.9089474678, -7.78659439087, -8.65151023865, -8.90391349792, -8.83986854553, -12.9047431946],
        "min": [-26.8631954193, -27.1175422668, -27.4965763092, -27.1101741791, -27.1761455536, -27.2570419312],
        "skew": [-4.26188278198, -2.53545069695, -2.8132147789, -1.96859455109, -1.40121459961, -0.355809688568],
        "var": [2.00473332405, 3.19377422333, 2.79591464996, 3.78273057938, 5.75112056732, 4.74319410324]
    }
},
"rhythm": {
    "beats_count": 60,
    "beats_loudness": {
        "dmean": 0.0193704999983,
        "dmean2": 0.0330144613981,
        "dvar": 0.00033241030178,
        "dvar2": 0.00099994475022,
        "kurt": -0.959802627563,
        "max": 0.102571725845,
        "mean": 0.0410767905414,
        "median": 0.0395975410938,
        "min": 9.1987029009e-05,
        "skew": 0.277475625277,
        "var": 0.000833783182316
    },
    "bpm": 122.033447266,
    "bpm_histogram_first_peak_bpm": 123,
    "bpm_histogram_first_peak_weight": 0.354166686535,
    "bpm_histogram_second_peak_bpm": 117,
    "bpm_histogram_second_peak_spread": 0.400000035763,
    "bpm_histogram_second_peak_weight": 0.101694911718,
    "danceability": 0.840282082558,
    "onset_rate": 3.5237660408,
    "beats_loudness_band_ratio": {
        "dmean": [0.19343970716, 0.16398614645, 0.0393867865205, 0.00892531499267, 0.0263532623649, 0.0189006254077],
        "dmean2": [0.319670051336, 0.271952539682, 0.067157573998, 0.0161951892078, 0.0443123541772, 0.0330670177937],
        "dvar": [0.0178461316973, 0.00952640268952, 0.00153993931599, 0.000108791675302, 0.000843385641929, 0.000541723391507],
        "dvar2": [0.0581105723977, 0.0303110238165, 0.00414779083803, 0.000294852739898, 0.00220739305951, 0.00134118844289],
        "kurt": [-0.622470140457, -0.484041929245, 0.222764492035, 1.65531015396, 3.12435388565, 6.61673355103],
        "max": [0.99723649025, 0.720765471458, 0.192496538162, 0.0467218458652, 0.140406653285, 0.137214913964],
        "mean": [0.589357614517, 0.373035728931, 0.0517105460167, 0.0111065180972, 0.0314738117158, 0.0228384193033],
        "median": [0.547863960266, 0.386705100536, 0.0366538614035, 0.0080088544637, 0.0248464457691, 0.0178444944322],
        "min": [0.17359931767, 0.00739594781771, 1.54160679813e-05, 5.30314673597e-06, 2.33958803619e-06, 1.40476652177e-06],
        "skew": [0.381352216005, -0.111384108663, 0.99933129549, 1.49929130077, 1.69850862026, 2.36312198639],
        "var": [0.0413975194097, 0.0274024736136, 0.00219723815098, 0.000123922014609, 0.00108407589141, 0.000696312694345]
    },
    "beats_position": [0.522448956966, 1.05650794506, 1.5673469305, 2.06657600403, 2.55419492722, 3.05342388153, 3.54104304314, 4.02866220474, 4.51628112793, 5.01551008224, 5.50312900543, 5.99074840546, 6.47836732864, 6.97759628296, 7.47682523727, 7.96444416046, 8.46367359161, 8.96290206909, 9.46213150024, 9.96135997772, 10.47219944, 10.9946479797, 11.5170974731, 12.0395460129, 12.538775444, 13.0496139526, 13.5488433838, 14.0712919235, 14.5821313858, 15.0697498322, 15.5689792633, 16.0565986633, 16.5558280945, 17.0434455872, 17.5310649872, 18.0186843872, 18.5063037872, 18.9939231873, 19.4815406799, 19.96916008, 20.45677948, 20.9676189423, 21.4784584045, 21.9660758972, 22.4536952972, 22.9413146973, 23.4289340973, 23.9165534973, 24.40417099, 24.89179039, 25.3910198212, 25.8902492523, 26.3778686523, 26.865486145, 27.353105545, 27.8407249451, 28.3399543762, 28.8391838074, 29.3268013, 29.8144207001],
    "bpm_histogram": [0, 0, 0, 0, 0, 0, 0, 0, 0, 0, 0, 0, 0, 0, 0, 0, 0, 0, 0, 0, 0, 0, 0, 0, 0, 0, 0, 0, 0, 0, 0, 0, 0, 0, 0, 0, 0, 0, 0, 0, 0, 0, 0, 0, 0, 0, 0, 0, 0, 0, 0, 0, 0, 0, 0, 0, 0, 0, 0, 0, 0, 0, 0, 0, 0, 0, 0, 0, 0, 0, 0, 0, 0, 0, 0, 0, 0, 0, 0, 0, 0, 0, 0, 0, 0, 0, 0, 0, 0, 0, 0, 0, 0, 0, 0, 0, 0, 0, 0, 0, 0, 0, 0, 0, 0, 0, 0, 0, 0, 0, 0, 0, 0.0169491525739, 0, 0, 0.0677966102958, 0, 0.101694911718, 0, 0, 0.288135588169, 0, 0, 0.525423705578, 0, 0, 0, 0, 0, 0, 0, 0, 0, 0, 0, 0, 0, 0, 0, 0, 0, 0, 0, 0, 0, 0, 0, 0, 0, 0, 0, 0, 0, 0, 0, 0, 0, 0, 0, 0, 0, 0, 0, 0, 0, 0, 0, 0, 0, 0, 0, 0, 0, 0, 0, 0, 0, 0, 0, 0, 0, 0, 0, 0, 0, 0, 0, 0, 0, 0, 0, 0, 0, 0, 0, 0, 0, 0, 0, 0, 0, 0, 0, 0, 0, 0, 0, 0, 0, 0, 0, 0, 0, 0, 0, 0, 0, 0, 0, 0, 0, 0, 0, 0, 0, 0, 0, 0, 0, 0, 0, 0, 0, 0, 0, 0, 0, 0, 0, 0, 0, 0, 0, 0, 0, 0, 0, 0, 0, 0]
},
"tonal": {
    "chords_changes_rate": 0.0184899847955,
    "chords_number_rate": 0.00770416017622,
    "chords_strength": {
        "dmean": 0.00609760032967,
        "dmean2": 0.0055684922263,
        "dvar": 2.86765134661e-05,
        "dvar2": 2.89081926894e-05,
        "kurt": -0.862511634827,
        "max": 0.651654601097,
        "mean": 0.530186474323,
        "median": 0.526449501514,
        "min": 0.383335530758,
        "skew": -0.102818153799,
        "var": 0.00371502758935
    },
    "hpcp_crest": {
        "dmean": 7.12166404724,
        "dmean2": 11.9792556763,
        "dvar": 49.1944046021,
        "dvar2": 106.564903259,
        "kurt": -0.784444570541,
        "max": 35.8634757996,
        "mean": 18.7593917847,
        "median": 17.0187625885,
        "min": 0,
        "skew": 0.581427872181,
        "var": 84.6754226685
    },
    "hpcp_entropy": {
        "dmean": 0.7164452672,
        "dmean2": 1.18399524689,
        "dvar": 0.446212500334,
        "dvar2": 1.07532680035,
        "kurt": -0.397850513458,
        "max": 4.32797527313,
        "mean": 1.52698910236,
        "median": 1.53081023693,
        "min": 0,
        "skew": 0.140261232853,
        "var": 0.734458744526
    },
    "key_edma": {
        "strength": 0.636788129807,
        "key": "F",
        "scale": "minor"
    },
    "key_krumhansl": {
        "strength": 0.619905948639,
        "key": "F",
        "scale": "minor"
    },
    "key_temperley": {
        "strength": 0.592810034752,
        "key": "F",
        "scale": "minor"
    },
    "tuning_diatonic_strength": 0.599015712738,
    "tuning_equal_tempered_deviation": 0.0335145145655,
    "tuning_frequency": 438.731048584,
    "tuning_nontempered_energy_ratio": 0.670174181461,
    "hpcp": {
        "dmean": [0.0411505289376, 0.0351890325546, 0.0238970927894, 0.0189124103636, 0.0219414234161, 0.0466940738261, 0.0657263472676, 0.141862675548, 0.270634263754, 0.14148658514, 0.24317188561, 0.065156377852, 0.0508561432362, 0.0556189864874, 0.0548853576183, 0.0631089061499, 0.0610140822828, 0.0269194040447, 0.0154341785237, 0.0210610739887, 0.0329791866243, 0.0277996510267, 0.0250826627016, 0.0325779803097, 0.034973885864, 0.0269276704639, 0.0181290265173, 0.0212042275816, 0.0404206439853, 0.1120890975, 0.139278709888, 0.106228530407, 0.0499160923064, 0.0283923391253, 0.0313492901623, 0.0422186292708],
        "dmean2": [0.0644375383854, 0.0628993064165, 0.0444947332144, 0.0332732610404, 0.0411189459264, 0.0883909985423, 0.120167441666, 0.255308061838, 0.501007378101, 0.24989400804, 0.44274649024, 0.124359995127, 0.0994222685695, 0.106214061379, 0.0973526388407, 0.110875822604, 0.108428232372, 0.0516767129302, 0.0290579143912, 0.0397120900452, 0.0583180524409, 0.0463381782174, 0.0460356734693, 0.058987736702, 0.0626816749573, 0.0484033748507, 0.0344408974051, 0.0404462330043, 0.07607550174, 0.192743986845, 0.231385812163, 0.189258426428, 0.096173286438, 0.0550030656159, 0.0601184032857, 0.0762980356812],
        "dvar": [0.00876687746495, 0.00845760945231, 0.00951419305056, 0.00542317517102, 0.00505405385047, 0.0223992262036, 0.0293903052807, 0.0578641779721, 0.0644830688834, 0.0646709054708, 0.0550099425018, 0.0301406178623, 0.0302768759429, 0.0324396602809, 0.0228384267539, 0.0329136513174, 0.0236025452614, 0.0142135675997, 0.0048670610413, 0.00827162805945, 0.0147793032229, 0.0100742839277, 0.0064883120358, 0.0100146327168, 0.0111283697188, 0.00744695868343, 0.00515635684133, 0.00555123388767, 0.0137386936694, 0.027057139203, 0.0366016402841, 0.0236136354506, 0.0166586041451, 0.00657126726583, 0.00988418981433, 0.0133881866932],
        "dvar2": [0.0168250910938, 0.0242299363017, 0.0274278186262, 0.0129133872688, 0.0138935549185, 0.0655879676342, 0.0791706219316, 0.147991165519, 0.200508788228, 0.146192908287, 0.160195976496, 0.0853035673499, 0.0881690829992, 0.0897459387779, 0.0620782189071, 0.0812606066465, 0.0679814517498, 0.039746824652, 0.0135817183182, 0.021339148283, 0.0368258692324, 0.0192868690938, 0.019195009023, 0.0283575691283, 0.0301009509712, 0.022265587002, 0.0149267334491, 0.0161087997258, 0.0392753593624, 0.0734874531627, 0.0914559140801, 0.0688629373908, 0.0473259799182, 0.0186846945435, 0.0282207708806, 0.0378226898611],
        "kurt": [17.1104927063, 26.6442508698, 93.2927246094, 73.1100006104, 58.3495368958, 42.2843971252, 18.3978614807, 7.00779628754, -1.01591145992, -0.7205722332, -0.261214017868, 30.1245040894, 38.1462860107, 29.2465667725, 9.14455223083, 5.18199825287, 12.7155599594, 79.2378082275, 112.494659424, 109.069023132, 29.8665542603, 27.7896575928, 55.6352729797, 50.0073852539, 19.0207958221, 31.6600570679, 174.979415894, 128.504760742, 51.8428153992, 4.66599225998, 1.82581472397, 6.74827480316, 39.2934532166, 56.5018310547, 72.9261474609, 26.8920307159],
        "max": [1, 0.787566065788, 1, 1, 0.862005054951, 1, 1, 1, 1, 1, 1, 1, 1, 1, 1, 1, 1, 1, 0.761504650116, 1, 1, 1, 0.836930394173, 1, 1, 0.978989899158, 0.941843509674, 0.919731616974, 1, 1, 1, 1, 1, 0.790682196617, 1, 0.943763017654],
        "mean": [0.0525143221021, 0.0311530716717, 0.0176807511598, 0.0200817622244, 0.0173701532185, 0.032407682389, 0.0550487339497, 0.0984431281686, 0.499199032784, 0.730905890465, 0.327278375626, 0.0374690853059, 0.0286152586341, 0.0353890694678, 0.0769309550524, 0.116512350738, 0.0700098872185, 0.0169947259128, 0.00968411564827, 0.0145322363824, 0.0364407151937, 0.0402730517089, 0.0190958622843, 0.0299246609211, 0.047541834414, 0.0289590656757, 0.0111287049949, 0.0130485408008, 0.0255439504981, 0.142505854368, 0.232541635633, 0.127546355128, 0.0287111513317, 0.0158382244408, 0.0180564150214, 0.0414071530104],
        "median": [0.00196311878972, 0.00160256354138, 0.000967937579844, 0.000847245217301, 0.000481993629364, 0.0025847889483, 0.00409544073045, 0.00444800872356, 0.540761590004, 1, 0.332052022219, 0.000761338800658, 0.00109320052434, 0.00119406031445, 0.00266906153411, 0.00848150346428, 0.00733574433252, 0.000807366566733, 0.000768296828028, 0.00090726907365, 0.00325579475611, 0.00376671459526, 0.00183969747741, 0.00207250006497, 0.0018730587326, 0.000613674113993, 0.000719674455468, 0.000730021449272, 0.00134646776132, 0.0661938413978, 0.137158557773, 0.0704636722803, 0.00127168011386, 0.000504794996232, 0.000536771083716, 0.00142662378494],
        "min": [0, 0, 0, 0, 0, 0, 0, 0, 0, 0, 0, 0, 0, 0, 0, 0, 0, 0, 0, 0, 0, 0, 0, 0, 0, 0, 0, 0, 0, 0, 0, 0, 0, 0, 0, 0],
        "skew": [3.80407381058, 4.64498519897, 8.99614429474, 8.12701034546, 6.94317007065, 6.16075515747, 4.17774772644, 2.69946098328, -0.180661410093, -1.03552651405, 0.5534055233, 5.22611474991, 6.07112312317, 5.36856842041, 3.13799309731, 2.61503958702, 3.5278942585, 8.66460800171, 10.0322713852, 9.79690170288, 5.44987821579, 5.2880358696, 6.94640398026, 6.22418022156, 4.18901824951, 5.20503044128, 11.8951864243, 9.82409000397, 6.61663627625, 2.11986494064, 1.57660794258, 2.33721399307, 5.8040266037, 6.64954328537, 7.70603847504, 4.68252277374],
        "var": [0.0170196723193, 0.00705893943086, 0.00659376755357, 0.00955540966243, 0.0053069726564, 0.0134623795748, 0.0252340957522, 0.0443891957402, 0.102468647063, 0.159696504474, 0.0696770772338, 0.0175080802292, 0.0163347963244, 0.0215077400208, 0.0429975762963, 0.0784170776606, 0.0310808550566, 0.00866025034338, 0.00295236916281, 0.00605367822573, 0.0210565906018, 0.0236561335623, 0.0051677916199, 0.00878947693855, 0.0202930886298, 0.0100890770555, 0.00288410042413, 0.00307088484988, 0.00811049435288, 0.0351951420307, 0.0673627480865, 0.0259241946042, 0.00953492242843, 0.00379340117797, 0.005684399046, 0.0128889037296]
    },
    "chords_histogram": [3.85208010674, 0, 0.308166414499, 0, 0, 0, 0, 6.62557792664, 6.47149467468, 64.7149429321, 0, 18.0277347565, 0, 0, 0, 0, 0, 0, 0, 0, 0, 0, 0, 0],
    "thpcp": [1, 0.447770893574, 0.0512638986111, 0.0391504019499, 0.0484180934727, 0.105254255235, 0.159408137202, 0.0957850888371, 0.0232515931129, 0.013249469921, 0.0198825001717, 0.0498569197953, 0.0551001876593, 0.0261262934655, 0.0409418791533, 0.065045081079, 0.0396207869053, 0.0152259068564, 0.0178525596857, 0.0349483452737, 0.194971546531, 0.318155378103, 0.174504488707, 0.0392815992236, 0.0216693077236, 0.0247041583061, 0.0566518269479, 0.0718482658267, 0.0426225475967, 0.0241901874542, 0.0274751689285, 0.0237652398646, 0.0443390645087, 0.0753157585859, 0.134686455131, 0.682986736298],
    "chords_key": "C",
    "chords_scale": "major"
}
}